{"filer":{"id":"senate_thomasr_tillis","full_name":"Thomas R Tillis","branch":"congress","chamber":"senate","party":"R","state":"NC","agency":null,"level":null,"office":"U.S. Senator · NC","photo_url":"https://unitedstates.github.io/images/congress/225x275/T000476.jpg"},"trades":[{"id":"senate_2d6428b6-c786-4e23-958f-a9d887b893d7_t0","filing_id":"senate_2d6428b6-c786-4e23-958f-a9d887b893d7","filer_id":"senate_thomasr_tillis","source_id":"senate_efd","transaction_date":"2022-08-30","notification_date":null,"filing_date":"2023-07-15","owner":"Self","ticker":"KD","asset_name":"Kyndryl Holdings, Inc. Common Stock","asset_type":"Stock","transaction_type":"Sale (Full)","amount_range_low":1001,"amount_range_high":15000,"amount_range_label":"$1,001 - $15,000","comment":null,"is_late":1,"days_to_file":319,"ingested_at":"2026-04-18 16:24:24","row_index":null,"notification_received_over_30d":null,"doc_url":"https://efdsearch.senate.gov/search/view/ptr/2d6428b6-c786-4e23-958f-a9d887b893d7/","filing_type":"PTR","ret_since":0,"excess_since":-86.93403747314356,"ret_30d":-19.774006124528853,"ret_1y":54.04897162567438},{"id":"senate_eaa9e663-e475-41a5-ac0d-3e107ed67481_t0","filing_id":"senate_eaa9e663-e475-41a5-ac0d-3e107ed67481","filer_id":"senate_thomasr_tillis","source_id":"senate_efd","transaction_date":"2018-12-20","notification_date":null,"filing_date":"2019-07-30","owner":"Joint","ticker":"CVS","asset_name":"CVS Health Corporation","asset_type":"Stock","transaction_type":"Sale (Full)","amount_range_low":1001,"amount_range_high":15000,"amount_range_label":"$1,001 - $15,000","comment":null,"is_late":1,"days_to_file":222,"ingested_at":"2026-04-18 16:24:25","row_index":null,"notification_received_over_30d":null,"doc_url":"https://efdsearch.senate.gov/search/view/ptr/eaa9e663-e475-41a5-ac0d-3e107ed67481/","filing_type":"PTR","ret_since":52.376651529143814,"excess_since":-148.7885465786108,"ret_30d":-2.34657808245369,"ret_1y":12.184112612979128},{"id":"senate_2c7b33c4-c85b-44a8-b8f7-cfe2f15961f5_t0","filing_id":"senate_2c7b33c4-c85b-44a8-b8f7-cfe2f15961f5","filer_id":"senate_thomasr_tillis","source_id":"senate_efd","transaction_date":"2018-12-20","notification_date":null,"filing_date":"2019-06-15","owner":"Joint","ticker":"CVS","asset_name":"CVS Health Corporation","asset_type":"Stock","transaction_type":"Sale (Partial)","amount_range_low":1001,"amount_range_high":15000,"amount_range_label":"$1,001 - $15,000","comment":null,"is_late":1,"days_to_file":177,"ingested_at":"2026-04-18 16:24:25","row_index":null,"notification_received_over_30d":null,"doc_url":"https://efdsearch.senate.gov/search/view/ptr/2c7b33c4-c85b-44a8-b8f7-cfe2f15961f5/","filing_type":"PTR","ret_since":52.376651529143814,"excess_since":-148.7885465786108,"ret_30d":-2.34657808245369,"ret_1y":12.184112612979128},{"id":"senate_44a21895-607d-48b6-89d9-0876caad796f_t0","filing_id":"senate_44a21895-607d-48b6-89d9-0876caad796f","filer_id":"senate_thomasr_tillis","source_id":"senate_efd","transaction_date":"2018-12-20","notification_date":null,"filing_date":"2019-02-27","owner":"Joint","ticker":"CVS","asset_name":"CVS Health Corporation","asset_type":"Stock","transaction_type":"Sale (Partial)","amount_range_low":1001,"amount_range_high":15000,"amount_range_label":"$1,001 - $15,000","comment":null,"is_late":1,"days_to_file":69,"ingested_at":"2026-04-18 16:24:25","row_index":null,"notification_received_over_30d":null,"doc_url":"https://efdsearch.senate.gov/search/view/ptr/44a21895-607d-48b6-89d9-0876caad796f/","filing_type":"PTR","ret_since":52.376651529143814,"excess_since":-148.7885465786108,"ret_30d":-2.34657808245369,"ret_1y":12.184112612979128},{"id":"senate_44a21895-607d-48b6-89d9-0876caad796f_t1","filing_id":"senate_44a21895-607d-48b6-89d9-0876caad796f","filer_id":"senate_thomasr_tillis","source_id":"senate_efd","transaction_date":"2018-12-20","notification_date":null,"filing_date":"2019-02-27","owner":"Joint","ticker":null,"asset_name":"Victory Portfolio Munder Multi-Cap Mutual Fund\n                                        \n                                        \n                                        \n                                            \n                                                \n                                                    Company: Munder Funds\n                                                    \n                                                         (Coloumbus, OH)","asset_type":"Other","transaction_type":"Sale (Full)","amount_range_low":1001,"amount_range_high":15000,"amount_range_label":"$1,001 - $15,000","comment":null,"is_late":1,"days_to_file":69,"ingested_at":"2026-04-18 16:24:25","row_index":null,"notification_received_over_30d":null,"doc_url":"https://efdsearch.senate.gov/search/view/ptr/44a21895-607d-48b6-89d9-0876caad796f/","filing_type":"PTR","ret_since":null,"excess_since":null,"ret_30d":null,"ret_1y":null},{"id":"senate_c7e41996-1636-4615-8d99-3fe47ca90f95_t0","filing_id":"senate_c7e41996-1636-4615-8d99-3fe47ca90f95","filer_id":"senate_thomasr_tillis","source_id":"senate_efd","transaction_date":"2017-02-03","notification_date":null,"filing_date":"2017-02-17","owner":"Joint","ticker":"AQFH","asset_name":"Aquesta Financial Holdings, Inc.","asset_type":"Stock","transaction_type":"Sale (Full)","amount_range_low":1001,"amount_range_high":15000,"amount_range_label":"$1,001 - $15,000","comment":null,"is_late":0,"days_to_file":14,"ingested_at":"2026-04-18 18:17:58","row_index":null,"notification_received_over_30d":null,"doc_url":"https://efdsearch.senate.gov/search/view/ptr/c7e41996-1636-4615-8d99-3fe47ca90f95/","filing_type":"PTR","ret_since":null,"excess_since":null,"ret_30d":null,"ret_1y":null},{"id":"senate_c7e41996-1636-4615-8d99-3fe47ca90f95_t1","filing_id":"senate_c7e41996-1636-4615-8d99-3fe47ca90f95","filer_id":"senate_thomasr_tillis","source_id":"senate_efd","transaction_date":"2017-02-01","notification_date":null,"filing_date":"2017-02-17","owner":"Joint","ticker":"AQFH","asset_name":"Aquesta Financial Holdings, Inc.","asset_type":"Stock","transaction_type":"Sale (Partial)","amount_range_low":15001,"amount_range_high":50000,"amount_range_label":"$15,001 - $50,000","comment":null,"is_late":0,"days_to_file":16,"ingested_at":"2026-04-18 18:17:58","row_index":null,"notification_received_over_30d":null,"doc_url":"https://efdsearch.senate.gov/search/view/ptr/c7e41996-1636-4615-8d99-3fe47ca90f95/","filing_type":"PTR","ret_since":null,"excess_since":null,"ret_30d":null,"ret_1y":null},{"id":"senate_c7e41996-1636-4615-8d99-3fe47ca90f95_t2","filing_id":"senate_c7e41996-1636-4615-8d99-3fe47ca90f95","filer_id":"senate_thomasr_tillis","source_id":"senate_efd","transaction_date":"2017-01-26","notification_date":null,"filing_date":"2017-02-17","owner":"Joint","ticker":null,"asset_name":"AQFH-Aquesta Financial Holdings, Inc.","asset_type":"Stock","transaction_type":"Sale (Partial)","amount_range_low":15001,"amount_range_high":50000,"amount_range_label":"$15,001 - $50,000","comment":null,"is_late":0,"days_to_file":22,"ingested_at":"2026-04-18 18:17:58","row_index":null,"notification_received_over_30d":null,"doc_url":"https://efdsearch.senate.gov/search/view/ptr/c7e41996-1636-4615-8d99-3fe47ca90f95/","filing_type":"PTR","ret_since":null,"excess_since":null,"ret_30d":null,"ret_1y":null},{"id":"senate_bbdeaa6d-dcb6-41fa-a5d5-cb5e5d10af6b_t0","filing_id":"senate_bbdeaa6d-dcb6-41fa-a5d5-cb5e5d10af6b","filer_id":"senate_thomasr_tillis","source_id":"senate_efd","transaction_date":"2015-02-13","notification_date":null,"filing_date":"2015-02-26","owner":"Joint","ticker":"JCOM","asset_name":"j2 Global, Inc. (NASDAQ)","asset_type":"Stock","transaction_type":"Sale (Full)","amount_range_low":1001,"amount_range_high":15000,"amount_range_label":"$1,001 - $15,000","comment":null,"is_late":0,"days_to_file":13,"ingested_at":"2026-04-18 18:17:58","row_index":null,"notification_received_over_30d":null,"doc_url":"https://efdsearch.senate.gov/search/view/ptr/bbdeaa6d-dcb6-41fa-a5d5-cb5e5d10af6b/","filing_type":"PTR","ret_since":null,"excess_since":null,"ret_30d":null,"ret_1y":null},{"id":"senate_bbdeaa6d-dcb6-41fa-a5d5-cb5e5d10af6b_t1","filing_id":"senate_bbdeaa6d-dcb6-41fa-a5d5-cb5e5d10af6b","filer_id":"senate_thomasr_tillis","source_id":"senate_efd","transaction_date":"2015-02-13","notification_date":null,"filing_date":"2015-02-26","owner":"Joint","ticker":"WST","asset_name":"West Pharmaceutical Services, Inc. (NYSE)","asset_type":"Stock","transaction_type":"Sale (Full)","amount_range_low":1001,"amount_range_high":15000,"amount_range_label":"$1,001 - $15,000","comment":null,"is_late":0,"days_to_file":13,"ingested_at":"2026-04-18 18:17:58","row_index":null,"notification_received_over_30d":null,"doc_url":"https://efdsearch.senate.gov/search/view/ptr/bbdeaa6d-dcb6-41fa-a5d5-cb5e5d10af6b/","filing_type":"PTR","ret_since":542.0837414849045,"excess_since":287.24056340309534,"ret_30d":8.354432410916973,"ret_1y":9.659207490862185},{"id":"senate_bbdeaa6d-dcb6-41fa-a5d5-cb5e5d10af6b_t2","filing_id":"senate_bbdeaa6d-dcb6-41fa-a5d5-cb5e5d10af6b","filer_id":"senate_thomasr_tillis","source_id":"senate_efd","transaction_date":"2015-02-13","notification_date":null,"filing_date":"2015-02-26","owner":"Joint","ticker":"WAL","asset_name":"Western Alliance Bancorporation (NYSE)","asset_type":"Stock","transaction_type":"Sale (Full)","amount_range_low":1001,"amount_range_high":15000,"amount_range_label":"$1,001 - $15,000","comment":null,"is_late":0,"days_to_file":13,"ingested_at":"2026-04-18 18:17:58","row_index":null,"notification_received_over_30d":null,"doc_url":"https://efdsearch.senate.gov/search/view/ptr/bbdeaa6d-dcb6-41fa-a5d5-cb5e5d10af6b/","filing_type":"PTR","ret_since":174.90402507820627,"excess_since":-79.93915300360291,"ret_30d":5.026179941469362,"ret_1y":3.5602110692663156},{"id":"senate_bbdeaa6d-dcb6-41fa-a5d5-cb5e5d10af6b_t3","filing_id":"senate_bbdeaa6d-dcb6-41fa-a5d5-cb5e5d10af6b","filer_id":"senate_thomasr_tillis","source_id":"senate_efd","transaction_date":"2015-02-13","notification_date":null,"filing_date":"2015-02-26","owner":"Joint","ticker":"WAGE","asset_name":"WageWorks, Inc. (NYSE)","asset_type":"Stock","transaction_type":"Sale (Full)","amount_range_low":1001,"amount_range_high":15000,"amount_range_label":"$1,001 - $15,000","comment":null,"is_late":0,"days_to_file":13,"ingested_at":"2026-04-18 18:17:58","row_index":null,"notification_received_over_30d":null,"doc_url":"https://efdsearch.senate.gov/search/view/ptr/bbdeaa6d-dcb6-41fa-a5d5-cb5e5d10af6b/","filing_type":"PTR","ret_since":null,"excess_since":null,"ret_30d":null,"ret_1y":null},{"id":"senate_bbdeaa6d-dcb6-41fa-a5d5-cb5e5d10af6b_t4","filing_id":"senate_bbdeaa6d-dcb6-41fa-a5d5-cb5e5d10af6b","filer_id":"senate_thomasr_tillis","source_id":"senate_efd","transaction_date":"2015-02-13","notification_date":null,"filing_date":"2015-02-26","owner":"Joint","ticker":"VSI","asset_name":"Vitamin Shoppe, Inc. (NYSE)","asset_type":"Stock","transaction_type":"Sale (Full)","amount_range_low":1001,"amount_range_high":15000,"amount_range_label":"$1,001 - $15,000","comment":null,"is_late":0,"days_to_file":13,"ingested_at":"2026-04-18 18:17:58","row_index":null,"notification_received_over_30d":null,"doc_url":"https://efdsearch.senate.gov/search/view/ptr/bbdeaa6d-dcb6-41fa-a5d5-cb5e5d10af6b/","filing_type":"PTR","ret_since":null,"excess_since":null,"ret_30d":null,"ret_1y":null},{"id":"senate_bbdeaa6d-dcb6-41fa-a5d5-cb5e5d10af6b_t5","filing_id":"senate_bbdeaa6d-dcb6-41fa-a5d5-cb5e5d10af6b","filer_id":"senate_thomasr_tillis","source_id":"senate_efd","transaction_date":"2015-02-13","notification_date":null,"filing_date":"2015-02-26","owner":"Joint","ticker":"TYPE","asset_name":"Monotype Imaging Holdings Inc. (NASDAQ)","asset_type":"Stock","transaction_type":"Sale (Full)","amount_range_low":1001,"amount_range_high":15000,"amount_range_label":"$1,001 - $15,000","comment":null,"is_late":0,"days_to_file":13,"ingested_at":"2026-04-18 18:17:58","row_index":null,"notification_received_over_30d":null,"doc_url":"https://efdsearch.senate.gov/search/view/ptr/bbdeaa6d-dcb6-41fa-a5d5-cb5e5d10af6b/","filing_type":"PTR","ret_since":null,"excess_since":null,"ret_30d":null,"ret_1y":null},{"id":"senate_bbdeaa6d-dcb6-41fa-a5d5-cb5e5d10af6b_t6","filing_id":"senate_bbdeaa6d-dcb6-41fa-a5d5-cb5e5d10af6b","filer_id":"senate_thomasr_tillis","source_id":"senate_efd","transaction_date":"2015-02-13","notification_date":null,"filing_date":"2015-02-26","owner":"Joint","ticker":"TXRH","asset_name":"Texas Roadhouse, Inc. (NASDAQ)","asset_type":"Stock","transaction_type":"Sale (Full)","amount_range_low":1001,"amount_range_high":15000,"amount_range_label":"$1,001 - $15,000","comment":null,"is_late":0,"days_to_file":13,"ingested_at":"2026-04-18 18:17:58","row_index":null,"notification_received_over_30d":null,"doc_url":"https://efdsearch.senate.gov/search/view/ptr/bbdeaa6d-dcb6-41fa-a5d5-cb5e5d10af6b/","filing_type":"PTR","ret_since":419.71669118079274,"excess_since":164.87351309898355,"ret_30d":6.649318377896768,"ret_1y":7.516618857044359},{"id":"senate_bbdeaa6d-dcb6-41fa-a5d5-cb5e5d10af6b_t7","filing_id":"senate_bbdeaa6d-dcb6-41fa-a5d5-cb5e5d10af6b","filer_id":"senate_thomasr_tillis","source_id":"senate_efd","transaction_date":"2015-02-13","notification_date":null,"filing_date":"2015-02-26","owner":"Joint","ticker":"TUMI","asset_name":"Tumi Holdings, Inc. (NYSE)","asset_type":"Stock","transaction_type":"Sale (Full)","amount_range_low":1001,"amount_range_high":15000,"amount_range_label":"$1,001 - $15,000","comment":null,"is_late":0,"days_to_file":13,"ingested_at":"2026-04-18 18:17:58","row_index":null,"notification_received_over_30d":null,"doc_url":"https://efdsearch.senate.gov/search/view/ptr/bbdeaa6d-dcb6-41fa-a5d5-cb5e5d10af6b/","filing_type":"PTR","ret_since":null,"excess_since":null,"ret_30d":null,"ret_1y":null},{"id":"senate_bbdeaa6d-dcb6-41fa-a5d5-cb5e5d10af6b_t8","filing_id":"senate_bbdeaa6d-dcb6-41fa-a5d5-cb5e5d10af6b","filer_id":"senate_thomasr_tillis","source_id":"senate_efd","transaction_date":"2015-02-13","notification_date":null,"filing_date":"2015-02-26","owner":"Joint","ticker":"TTC","asset_name":"The Toro Company (NYSE)","asset_type":"Stock","transaction_type":"Sale (Full)","amount_range_low":1001,"amount_range_high":15000,"amount_range_label":"$1,001 - $15,000","comment":null,"is_late":0,"days_to_file":13,"ingested_at":"2026-04-18 18:17:58","row_index":null,"notification_received_over_30d":null,"doc_url":"https://efdsearch.senate.gov/search/view/ptr/bbdeaa6d-dcb6-41fa-a5d5-cb5e5d10af6b/","filing_type":"PTR","ret_since":169.28582093709957,"excess_since":-85.55735714470961,"ret_30d":-1.5627277285642653,"ret_1y":8.850587776477798},{"id":"senate_bbdeaa6d-dcb6-41fa-a5d5-cb5e5d10af6b_t9","filing_id":"senate_bbdeaa6d-dcb6-41fa-a5d5-cb5e5d10af6b","filer_id":"senate_thomasr_tillis","source_id":"senate_efd","transaction_date":"2015-02-13","notification_date":null,"filing_date":"2015-02-26","owner":"Spouse","ticker":"TNGO","asset_name":"Tangoe, Inc. (NASDAQ)","asset_type":"Stock","transaction_type":"Sale (Full)","amount_range_low":1001,"amount_range_high":15000,"amount_range_label":"$1,001 - $15,000","comment":null,"is_late":0,"days_to_file":13,"ingested_at":"2026-04-18 18:17:58","row_index":null,"notification_received_over_30d":null,"doc_url":"https://efdsearch.senate.gov/search/view/ptr/bbdeaa6d-dcb6-41fa-a5d5-cb5e5d10af6b/","filing_type":"PTR","ret_since":null,"excess_since":null,"ret_30d":null,"ret_1y":null},{"id":"senate_bbdeaa6d-dcb6-41fa-a5d5-cb5e5d10af6b_t10","filing_id":"senate_bbdeaa6d-dcb6-41fa-a5d5-cb5e5d10af6b","filer_id":"senate_thomasr_tillis","source_id":"senate_efd","transaction_date":"2015-02-13","notification_date":null,"filing_date":"2015-02-26","owner":"Joint","ticker":"THS","asset_name":"Treehouse Foods, Inc. (NYSE)","asset_type":"Stock","transaction_type":"Sale (Full)","amount_range_low":1001,"amount_range_high":15000,"amount_range_label":"$1,001 - $15,000","comment":null,"is_late":0,"days_to_file":13,"ingested_at":"2026-04-18 18:17:58","row_index":null,"notification_received_over_30d":null,"doc_url":"https://efdsearch.senate.gov/search/view/ptr/bbdeaa6d-dcb6-41fa-a5d5-cb5e5d10af6b/","filing_type":"PTR","ret_since":null,"excess_since":null,"ret_30d":null,"ret_1y":null},{"id":"senate_bbdeaa6d-dcb6-41fa-a5d5-cb5e5d10af6b_t11","filing_id":"senate_bbdeaa6d-dcb6-41fa-a5d5-cb5e5d10af6b","filer_id":"senate_thomasr_tillis","source_id":"senate_efd","transaction_date":"2015-02-13","notification_date":null,"filing_date":"2015-02-26","owner":"Joint","ticker":"THRM","asset_name":"Gentherm Incorporated (NASDAQ)","asset_type":"Stock","transaction_type":"Sale (Full)","amount_range_low":1001,"amount_range_high":15000,"amount_range_label":"$1,001 - $15,000","comment":null,"is_late":0,"days_to_file":13,"ingested_at":"2026-04-18 18:17:58","row_index":null,"notification_received_over_30d":null,"doc_url":"https://efdsearch.senate.gov/search/view/ptr/bbdeaa6d-dcb6-41fa-a5d5-cb5e5d10af6b/","filing_type":"PTR","ret_since":null,"excess_since":null,"ret_30d":null,"ret_1y":null},{"id":"senate_bbdeaa6d-dcb6-41fa-a5d5-cb5e5d10af6b_t12","filing_id":"senate_bbdeaa6d-dcb6-41fa-a5d5-cb5e5d10af6b","filer_id":"senate_thomasr_tillis","source_id":"senate_efd","transaction_date":"2015-02-13","notification_date":null,"filing_date":"2015-02-26","owner":"Joint","ticker":"TECH","asset_name":"Bio-Techne Corp. (NASDAQ)","asset_type":"Stock","transaction_type":"Sale (Full)","amount_range_low":1001,"amount_range_high":15000,"amount_range_label":"$1,001 - $15,000","comment":null,"is_late":0,"days_to_file":13,"ingested_at":"2026-04-18 18:17:58","row_index":null,"notification_received_over_30d":null,"doc_url":"https://efdsearch.senate.gov/search/view/ptr/bbdeaa6d-dcb6-41fa-a5d5-cb5e5d10af6b/","filing_type":"PTR","ret_since":135.1125684456115,"excess_since":-119.7306096361977,"ret_30d":3.054644721492829,"ret_1y":-7.557342225718792},{"id":"senate_bbdeaa6d-dcb6-41fa-a5d5-cb5e5d10af6b_t13","filing_id":"senate_bbdeaa6d-dcb6-41fa-a5d5-cb5e5d10af6b","filer_id":"senate_thomasr_tillis","source_id":"senate_efd","transaction_date":"2015-02-13","notification_date":null,"filing_date":"2015-02-26","owner":"Joint","ticker":"TCBI","asset_name":"Texas Capital BancShares Inc. (NASDAQ)","asset_type":"Stock","transaction_type":"Sale (Full)","amount_range_low":1001,"amount_range_high":15000,"amount_range_label":"$1,001 - $15,000","comment":null,"is_late":0,"days_to_file":13,"ingested_at":"2026-04-18 18:17:58","row_index":null,"notification_received_over_30d":null,"doc_url":"https://efdsearch.senate.gov/search/view/ptr/bbdeaa6d-dcb6-41fa-a5d5-cb5e5d10af6b/","filing_type":"PTR","ret_since":105.31849499139119,"excess_since":-149.524683090418,"ret_30d":2.2263489351127914,"ret_1y":-29.973196462420592},{"id":"senate_bbdeaa6d-dcb6-41fa-a5d5-cb5e5d10af6b_t14","filing_id":"senate_bbdeaa6d-dcb6-41fa-a5d5-cb5e5d10af6b","filer_id":"senate_thomasr_tillis","source_id":"senate_efd","transaction_date":"2015-02-13","notification_date":null,"filing_date":"2015-02-26","owner":"Joint","ticker":"SXT","asset_name":"Sensient Technologies Corporation (NYSE)","asset_type":"Stock","transaction_type":"Sale (Full)","amount_range_low":1001,"amount_range_high":15000,"amount_range_label":"$1,001 - $15,000","comment":null,"is_late":0,"days_to_file":13,"ingested_at":"2026-04-18 18:17:58","row_index":null,"notification_received_over_30d":null,"doc_url":"https://efdsearch.senate.gov/search/view/ptr/bbdeaa6d-dcb6-41fa-a5d5-cb5e5d10af6b/","filing_type":"PTR","ret_since":null,"excess_since":null,"ret_30d":null,"ret_1y":null},{"id":"senate_bbdeaa6d-dcb6-41fa-a5d5-cb5e5d10af6b_t15","filing_id":"senate_bbdeaa6d-dcb6-41fa-a5d5-cb5e5d10af6b","filer_id":"senate_thomasr_tillis","source_id":"senate_efd","transaction_date":"2015-02-13","notification_date":null,"filing_date":"2015-02-26","owner":"Joint","ticker":"SWI","asset_name":"SolarWinds, Inc. (NYSE)","asset_type":"Stock","transaction_type":"Sale (Full)","amount_range_low":1001,"amount_range_high":15000,"amount_range_label":"$1,001 - $15,000","comment":null,"is_late":0,"days_to_file":13,"ingested_at":"2026-04-18 18:17:58","row_index":null,"notification_received_over_30d":null,"doc_url":"https://efdsearch.senate.gov/search/view/ptr/bbdeaa6d-dcb6-41fa-a5d5-cb5e5d10af6b/","filing_type":"PTR","ret_since":null,"excess_since":null,"ret_30d":null,"ret_1y":null},{"id":"senate_bbdeaa6d-dcb6-41fa-a5d5-cb5e5d10af6b_t16","filing_id":"senate_bbdeaa6d-dcb6-41fa-a5d5-cb5e5d10af6b","filer_id":"senate_thomasr_tillis","source_id":"senate_efd","transaction_date":"2015-02-13","notification_date":null,"filing_date":"2015-02-26","owner":"Joint","ticker":"SSB","asset_name":"South State Corporation (NASDAQ)","asset_type":"Stock","transaction_type":"Sale (Full)","amount_range_low":1001,"amount_range_high":15000,"amount_range_label":"$1,001 - $15,000","comment":null,"is_late":0,"days_to_file":13,"ingested_at":"2026-04-18 18:17:58","row_index":null,"notification_received_over_30d":null,"doc_url":"https://efdsearch.senate.gov/search/view/ptr/bbdeaa6d-dcb6-41fa-a5d5-cb5e5d10af6b/","filing_type":"PTR","ret_since":49.29296172497028,"excess_since":-205.55021635683892,"ret_30d":3.9040900873686493,"ret_1y":-4.011676750070126},{"id":"senate_bbdeaa6d-dcb6-41fa-a5d5-cb5e5d10af6b_t17","filing_id":"senate_bbdeaa6d-dcb6-41fa-a5d5-cb5e5d10af6b","filer_id":"senate_thomasr_tillis","source_id":"senate_efd","transaction_date":"2015-02-13","notification_date":null,"filing_date":"2015-02-26","owner":"Joint","ticker":"SQI","asset_name":"SciQuest, Inc. (NASDAQ)","asset_type":"Stock","transaction_type":"Sale (Full)","amount_range_low":1001,"amount_range_high":15000,"amount_range_label":"$1,001 - $15,000","comment":null,"is_late":0,"days_to_file":13,"ingested_at":"2026-04-18 18:17:58","row_index":null,"notification_received_over_30d":null,"doc_url":"https://efdsearch.senate.gov/search/view/ptr/bbdeaa6d-dcb6-41fa-a5d5-cb5e5d10af6b/","filing_type":"PTR","ret_since":null,"excess_since":null,"ret_30d":null,"ret_1y":null},{"id":"senate_bbdeaa6d-dcb6-41fa-a5d5-cb5e5d10af6b_t18","filing_id":"senate_bbdeaa6d-dcb6-41fa-a5d5-cb5e5d10af6b","filer_id":"senate_thomasr_tillis","source_id":"senate_efd","transaction_date":"2015-02-13","notification_date":null,"filing_date":"2015-02-26","owner":"Joint","ticker":"SPSC","asset_name":"SPS Commerce, Inc. (NASDAQ)","asset_type":"Stock","transaction_type":"Sale (Full)","amount_range_low":1001,"amount_range_high":15000,"amount_range_label":"$1,001 - $15,000","comment":null,"is_late":0,"days_to_file":13,"ingested_at":"2026-04-18 18:17:58","row_index":null,"notification_received_over_30d":null,"doc_url":"https://efdsearch.senate.gov/search/view/ptr/bbdeaa6d-dcb6-41fa-a5d5-cb5e5d10af6b/","filing_type":"PTR","ret_since":60.43281503130182,"excess_since":-194.41036305050736,"ret_30d":-0.40941480011075393,"ret_1y":-39.099280746326365},{"id":"senate_bbdeaa6d-dcb6-41fa-a5d5-cb5e5d10af6b_t19","filing_id":"senate_bbdeaa6d-dcb6-41fa-a5d5-cb5e5d10af6b","filer_id":"senate_thomasr_tillis","source_id":"senate_efd","transaction_date":"2015-02-13","notification_date":null,"filing_date":"2015-02-26","owner":"Joint","ticker":"SMTC","asset_name":"Semtech Corporation (NASDAQ)","asset_type":"Stock","transaction_type":"Sale (Full)","amount_range_low":1001,"amount_range_high":15000,"amount_range_label":"$1,001 - $15,000","comment":null,"is_late":0,"days_to_file":13,"ingested_at":"2026-04-18 18:17:58","row_index":null,"notification_received_over_30d":null,"doc_url":"https://efdsearch.senate.gov/search/view/ptr/bbdeaa6d-dcb6-41fa-a5d5-cb5e5d10af6b/","filing_type":"PTR","ret_since":544.2846250755432,"excess_since":289.441446993734,"ret_30d":3.355456560663707,"ret_1y":-38.16371703977532},{"id":"senate_bbdeaa6d-dcb6-41fa-a5d5-cb5e5d10af6b_t20","filing_id":"senate_bbdeaa6d-dcb6-41fa-a5d5-cb5e5d10af6b","filer_id":"senate_thomasr_tillis","source_id":"senate_efd","transaction_date":"2015-02-13","notification_date":null,"filing_date":"2015-02-26","owner":"Joint","ticker":"SIGI","asset_name":"Selective Insurance Group Inc. (NASDAQ)","asset_type":"Stock","transaction_type":"Sale (Full)","amount_range_low":1001,"amount_range_high":15000,"amount_range_label":"$1,001 - $15,000","comment":null,"is_late":0,"days_to_file":13,"ingested_at":"2026-04-18 18:17:58","row_index":null,"notification_received_over_30d":null,"doc_url":"https://efdsearch.senate.gov/search/view/ptr/bbdeaa6d-dcb6-41fa-a5d5-cb5e5d10af6b/","filing_type":"PTR","ret_since":237.8654984621305,"excess_since":-16.977679619678696,"ret_30d":6.761690178549021,"ret_1y":23.757309411538344},{"id":"senate_bbdeaa6d-dcb6-41fa-a5d5-cb5e5d10af6b_t21","filing_id":"senate_bbdeaa6d-dcb6-41fa-a5d5-cb5e5d10af6b","filer_id":"senate_thomasr_tillis","source_id":"senate_efd","transaction_date":"2015-02-13","notification_date":null,"filing_date":"2015-02-26","owner":"Joint","ticker":"SHOO","asset_name":"Steven Madden, Ltd. (NASDAQ)","asset_type":"Stock","transaction_type":"Sale (Full)","amount_range_low":1001,"amount_range_high":15000,"amount_range_label":"$1,001 - $15,000","comment":null,"is_late":0,"days_to_file":13,"ingested_at":"2026-04-18 18:17:58","row_index":null,"notification_received_over_30d":null,"doc_url":"https://efdsearch.senate.gov/search/view/ptr/bbdeaa6d-dcb6-41fa-a5d5-cb5e5d10af6b/","filing_type":"PTR","ret_since":null,"excess_since":null,"ret_30d":null,"ret_1y":null},{"id":"senate_bbdeaa6d-dcb6-41fa-a5d5-cb5e5d10af6b_t22","filing_id":"senate_bbdeaa6d-dcb6-41fa-a5d5-cb5e5d10af6b","filer_id":"senate_thomasr_tillis","source_id":"senate_efd","transaction_date":"2015-02-13","notification_date":null,"filing_date":"2015-02-26","owner":"Joint","ticker":"SGY","asset_name":"Stone Energy Corp. (NYSE)","asset_type":"Stock","transaction_type":"Sale (Full)","amount_range_low":1001,"amount_range_high":15000,"amount_range_label":"$1,001 - $15,000","comment":null,"is_late":0,"days_to_file":13,"ingested_at":"2026-04-18 18:17:58","row_index":null,"notification_received_over_30d":null,"doc_url":"https://efdsearch.senate.gov/search/view/ptr/bbdeaa6d-dcb6-41fa-a5d5-cb5e5d10af6b/","filing_type":"PTR","ret_since":null,"excess_since":null,"ret_30d":null,"ret_1y":null},{"id":"senate_bbdeaa6d-dcb6-41fa-a5d5-cb5e5d10af6b_t23","filing_id":"senate_bbdeaa6d-dcb6-41fa-a5d5-cb5e5d10af6b","filer_id":"senate_thomasr_tillis","source_id":"senate_efd","transaction_date":"2015-02-13","notification_date":null,"filing_date":"2015-02-26","owner":"Joint","ticker":"RRTS","asset_name":"Roadrunner Transportation Systems, Inc. (NYSE)","asset_type":"Stock","transaction_type":"Sale (Full)","amount_range_low":1001,"amount_range_high":15000,"amount_range_label":"$1,001 - $15,000","comment":null,"is_late":0,"days_to_file":13,"ingested_at":"2026-04-18 18:17:58","row_index":null,"notification_received_over_30d":null,"doc_url":"https://efdsearch.senate.gov/search/view/ptr/bbdeaa6d-dcb6-41fa-a5d5-cb5e5d10af6b/","filing_type":"PTR","ret_since":null,"excess_since":null,"ret_30d":null,"ret_1y":null},{"id":"senate_bbdeaa6d-dcb6-41fa-a5d5-cb5e5d10af6b_t24","filing_id":"senate_bbdeaa6d-dcb6-41fa-a5d5-cb5e5d10af6b","filer_id":"senate_thomasr_tillis","source_id":"senate_efd","transaction_date":"2015-02-13","notification_date":null,"filing_date":"2015-02-26","owner":"Joint","ticker":"ROLL","asset_name":"RBC Bearings Inc. (NASDAQ)","asset_type":"Stock","transaction_type":"Sale (Full)","amount_range_low":1001,"amount_range_high":15000,"amount_range_label":"$1,001 - $15,000","comment":null,"is_late":0,"days_to_file":13,"ingested_at":"2026-04-18 18:17:58","row_index":null,"notification_received_over_30d":null,"doc_url":"https://efdsearch.senate.gov/search/view/ptr/bbdeaa6d-dcb6-41fa-a5d5-cb5e5d10af6b/","filing_type":"PTR","ret_since":null,"excess_since":null,"ret_30d":null,"ret_1y":null},{"id":"senate_bbdeaa6d-dcb6-41fa-a5d5-cb5e5d10af6b_t25","filing_id":"senate_bbdeaa6d-dcb6-41fa-a5d5-cb5e5d10af6b","filer_id":"senate_thomasr_tillis","source_id":"senate_efd","transaction_date":"2015-02-13","notification_date":null,"filing_date":"2015-02-26","owner":"Joint","ticker":"RBA","asset_name":"Ritchie Bros. Auctioneers Incorporated (NYSE)","asset_type":"Stock","transaction_type":"Sale (Full)","amount_range_low":1001,"amount_range_high":15000,"amount_range_label":"$1,001 - $15,000","comment":null,"is_late":0,"days_to_file":13,"ingested_at":"2026-04-18 18:17:58","row_index":null,"notification_received_over_30d":null,"doc_url":"https://efdsearch.senate.gov/search/view/ptr/bbdeaa6d-dcb6-41fa-a5d5-cb5e5d10af6b/","filing_type":"PTR","ret_since":306.70161354130454,"excess_since":51.858435459495354,"ret_30d":-6.514413443502061,"ret_1y":-13.178579824292552},{"id":"senate_bbdeaa6d-dcb6-41fa-a5d5-cb5e5d10af6b_t26","filing_id":"senate_bbdeaa6d-dcb6-41fa-a5d5-cb5e5d10af6b","filer_id":"senate_thomasr_tillis","source_id":"senate_efd","transaction_date":"2015-02-13","notification_date":null,"filing_date":"2015-02-26","owner":"Joint","ticker":"RAVN","asset_name":"Raven Industries Inc. (NASDAQ)","asset_type":"Stock","transaction_type":"Sale (Full)","amount_range_low":1001,"amount_range_high":15000,"amount_range_label":"$1,001 - $15,000","comment":null,"is_late":0,"days_to_file":13,"ingested_at":"2026-04-18 18:17:58","row_index":null,"notification_received_over_30d":null,"doc_url":"https://efdsearch.senate.gov/search/view/ptr/bbdeaa6d-dcb6-41fa-a5d5-cb5e5d10af6b/","filing_type":"PTR","ret_since":null,"excess_since":null,"ret_30d":null,"ret_1y":null},{"id":"senate_bbdeaa6d-dcb6-41fa-a5d5-cb5e5d10af6b_t27","filing_id":"senate_bbdeaa6d-dcb6-41fa-a5d5-cb5e5d10af6b","filer_id":"senate_thomasr_tillis","source_id":"senate_efd","transaction_date":"2015-02-13","notification_date":null,"filing_date":"2015-02-26","owner":"Joint","ticker":"QLIK","asset_name":"Qlik Technologies, Inc. (NASDAQ)","asset_type":"Stock","transaction_type":"Sale (Full)","amount_range_low":1001,"amount_range_high":15000,"amount_range_label":"$1,001 - $15,000","comment":null,"is_late":0,"days_to_file":13,"ingested_at":"2026-04-18 18:17:58","row_index":null,"notification_received_over_30d":null,"doc_url":"https://efdsearch.senate.gov/search/view/ptr/bbdeaa6d-dcb6-41fa-a5d5-cb5e5d10af6b/","filing_type":"PTR","ret_since":null,"excess_since":null,"ret_30d":null,"ret_1y":null},{"id":"senate_bbdeaa6d-dcb6-41fa-a5d5-cb5e5d10af6b_t28","filing_id":"senate_bbdeaa6d-dcb6-41fa-a5d5-cb5e5d10af6b","filer_id":"senate_thomasr_tillis","source_id":"senate_efd","transaction_date":"2015-02-13","notification_date":null,"filing_date":"2015-02-26","owner":"Joint","ticker":"PRLB","asset_name":"Proto Labs, Inc. (NYSE)","asset_type":"Stock","transaction_type":"Sale (Full)","amount_range_low":1001,"amount_range_high":15000,"amount_range_label":"$1,001 - $15,000","comment":null,"is_late":0,"days_to_file":13,"ingested_at":"2026-04-18 18:17:58","row_index":null,"notification_received_over_30d":null,"doc_url":"https://efdsearch.senate.gov/search/view/ptr/bbdeaa6d-dcb6-41fa-a5d5-cb5e5d10af6b/","filing_type":"PTR","ret_since":10.378378790778083,"excess_since":-244.4647992910311,"ret_30d":-5.297294822899071,"ret_1y":-17.97297194197371},{"id":"senate_bbdeaa6d-dcb6-41fa-a5d5-cb5e5d10af6b_t29","filing_id":"senate_bbdeaa6d-dcb6-41fa-a5d5-cb5e5d10af6b","filer_id":"senate_thomasr_tillis","source_id":"senate_efd","transaction_date":"2015-02-13","notification_date":null,"filing_date":"2015-02-26","owner":"Joint","ticker":"PRIM","asset_name":"Primoris Services Corporation (NASDAQ)","asset_type":"Stock","transaction_type":"Sale (Full)","amount_range_low":1001,"amount_range_high":15000,"amount_range_label":"$1,001 - $15,000","comment":null,"is_late":0,"days_to_file":13,"ingested_at":"2026-04-18 18:17:58","row_index":null,"notification_received_over_30d":null,"doc_url":"https://efdsearch.senate.gov/search/view/ptr/bbdeaa6d-dcb6-41fa-a5d5-cb5e5d10af6b/","filing_type":"PTR","ret_since":394.7031882421622,"excess_since":139.860010160353,"ret_30d":-22.100457702714365,"ret_1y":-11.141555144106288},{"id":"senate_bbdeaa6d-dcb6-41fa-a5d5-cb5e5d10af6b_t30","filing_id":"senate_bbdeaa6d-dcb6-41fa-a5d5-cb5e5d10af6b","filer_id":"senate_thomasr_tillis","source_id":"senate_efd","transaction_date":"2015-02-13","notification_date":null,"filing_date":"2015-02-26","owner":"Joint","ticker":"PRAA","asset_name":"PRA Group, Inc. (NASDAQ)","asset_type":"Stock","transaction_type":"Sale (Full)","amount_range_low":1001,"amount_range_high":15000,"amount_range_label":"$1,001 - $15,000","comment":null,"is_late":0,"days_to_file":13,"ingested_at":"2026-04-18 18:17:58","row_index":null,"notification_received_over_30d":null,"doc_url":"https://efdsearch.senate.gov/search/view/ptr/bbdeaa6d-dcb6-41fa-a5d5-cb5e5d10af6b/","filing_type":"PTR","ret_since":-69.92795003426644,"excess_since":-324.7711281160756,"ret_30d":0.739475497225231,"ret_1y":-48.54001037939022},{"id":"senate_bbdeaa6d-dcb6-41fa-a5d5-cb5e5d10af6b_t31","filing_id":"senate_bbdeaa6d-dcb6-41fa-a5d5-cb5e5d10af6b","filer_id":"senate_thomasr_tillis","source_id":"senate_efd","transaction_date":"2015-02-13","notification_date":null,"filing_date":"2015-02-26","owner":"Joint","ticker":"PRA","asset_name":"ProAssurance Corporation (NYSE)","asset_type":"Stock","transaction_type":"Sale (Full)","amount_range_low":1001,"amount_range_high":15000,"amount_range_label":"$1,001 - $15,000","comment":null,"is_late":0,"days_to_file":13,"ingested_at":"2026-04-18 18:17:58","row_index":null,"notification_received_over_30d":null,"doc_url":"https://efdsearch.senate.gov/search/view/ptr/bbdeaa6d-dcb6-41fa-a5d5-cb5e5d10af6b/","filing_type":"PTR","ret_since":-46.16059690719958,"excess_since":-301.0037749890088,"ret_30d":0.3071509083465037,"ret_1y":8.688018704234933},{"id":"senate_bbdeaa6d-dcb6-41fa-a5d5-cb5e5d10af6b_t32","filing_id":"senate_bbdeaa6d-dcb6-41fa-a5d5-cb5e5d10af6b","filer_id":"senate_thomasr_tillis","source_id":"senate_efd","transaction_date":"2015-02-13","notification_date":null,"filing_date":"2015-02-26","owner":"Joint","ticker":"POWI","asset_name":"Power Integrations Inc. (NASDAQ)","asset_type":"Stock","transaction_type":"Sale (Full)","amount_range_low":1001,"amount_range_high":15000,"amount_range_label":"$1,001 - $15,000","comment":null,"is_late":0,"days_to_file":13,"ingested_at":"2026-04-18 18:17:58","row_index":null,"notification_received_over_30d":null,"doc_url":"https://efdsearch.senate.gov/search/view/ptr/bbdeaa6d-dcb6-41fa-a5d5-cb5e5d10af6b/","filing_type":"PTR","ret_since":219.20335905251088,"excess_since":-35.63981902929831,"ret_30d":2.5214710024805638,"ret_1y":-16.86460738066211},{"id":"senate_bbdeaa6d-dcb6-41fa-a5d5-cb5e5d10af6b_t33","filing_id":"senate_bbdeaa6d-dcb6-41fa-a5d5-cb5e5d10af6b","filer_id":"senate_thomasr_tillis","source_id":"senate_efd","transaction_date":"2015-02-13","notification_date":null,"filing_date":"2015-02-26","owner":"Joint","ticker":"PLT","asset_name":"Plantronics, Inc. (NYSE)","asset_type":"Stock","transaction_type":"Sale (Full)","amount_range_low":1001,"amount_range_high":15000,"amount_range_label":"$1,001 - $15,000","comment":null,"is_late":0,"days_to_file":13,"ingested_at":"2026-04-18 18:17:58","row_index":null,"notification_received_over_30d":null,"doc_url":"https://efdsearch.senate.gov/search/view/ptr/bbdeaa6d-dcb6-41fa-a5d5-cb5e5d10af6b/","filing_type":"PTR","ret_since":null,"excess_since":null,"ret_30d":null,"ret_1y":null},{"id":"senate_bbdeaa6d-dcb6-41fa-a5d5-cb5e5d10af6b_t34","filing_id":"senate_bbdeaa6d-dcb6-41fa-a5d5-cb5e5d10af6b","filer_id":"senate_thomasr_tillis","source_id":"senate_efd","transaction_date":"2015-02-13","notification_date":null,"filing_date":"2015-02-26","owner":"Joint","ticker":"PLKI","asset_name":"Popeyes Louisiana Kitchen, Inc. (NASDAQ)","asset_type":"Stock","transaction_type":"Sale (Full)","amount_range_low":1001,"amount_range_high":15000,"amount_range_label":"$1,001 - $15,000","comment":null,"is_late":0,"days_to_file":13,"ingested_at":"2026-04-18 18:17:58","row_index":null,"notification_received_over_30d":null,"doc_url":"https://efdsearch.senate.gov/search/view/ptr/bbdeaa6d-dcb6-41fa-a5d5-cb5e5d10af6b/","filing_type":"PTR","ret_since":null,"excess_since":null,"ret_30d":null,"ret_1y":null},{"id":"senate_bbdeaa6d-dcb6-41fa-a5d5-cb5e5d10af6b_t35","filing_id":"senate_bbdeaa6d-dcb6-41fa-a5d5-cb5e5d10af6b","filer_id":"senate_thomasr_tillis","source_id":"senate_efd","transaction_date":"2015-02-13","notification_date":null,"filing_date":"2015-02-26","owner":"Joint","ticker":"PEB","asset_name":"Pebblebrook Hotel Trust (NYSE)","asset_type":"Stock","transaction_type":"Sale (Full)","amount_range_low":1001,"amount_range_high":15000,"amount_range_label":"$1,001 - $15,000","comment":null,"is_late":0,"days_to_file":13,"ingested_at":"2026-04-18 18:17:58","row_index":null,"notification_received_over_30d":null,"doc_url":"https://efdsearch.senate.gov/search/view/ptr/bbdeaa6d-dcb6-41fa-a5d5-cb5e5d10af6b/","filing_type":"PTR","ret_since":-61.78031954203694,"excess_since":-316.6234976238461,"ret_30d":-4.348715982078556,"ret_1y":-48.53001363804909},{"id":"senate_bbdeaa6d-dcb6-41fa-a5d5-cb5e5d10af6b_t36","filing_id":"senate_bbdeaa6d-dcb6-41fa-a5d5-cb5e5d10af6b","filer_id":"senate_thomasr_tillis","source_id":"senate_efd","transaction_date":"2015-02-13","notification_date":null,"filing_date":"2015-02-26","owner":"Joint","ticker":"PBH","asset_name":"Prestige Brands Holdings, Inc. (NYSE)","asset_type":"Stock","transaction_type":"Sale (Full)","amount_range_low":1001,"amount_range_high":15000,"amount_range_label":"$1,001 - $15,000","comment":null,"is_late":0,"days_to_file":13,"ingested_at":"2026-04-18 18:17:58","row_index":null,"notification_received_over_30d":null,"doc_url":"https://efdsearch.senate.gov/search/view/ptr/bbdeaa6d-dcb6-41fa-a5d5-cb5e5d10af6b/","filing_type":"PTR","ret_since":null,"excess_since":null,"ret_30d":null,"ret_1y":null},{"id":"senate_bbdeaa6d-dcb6-41fa-a5d5-cb5e5d10af6b_t37","filing_id":"senate_bbdeaa6d-dcb6-41fa-a5d5-cb5e5d10af6b","filer_id":"senate_thomasr_tillis","source_id":"senate_efd","transaction_date":"2015-02-13","notification_date":null,"filing_date":"2015-02-26","owner":"Joint","ticker":"OMCL","asset_name":"Omnicell, Inc. (NASDAQ)","asset_type":"Stock","transaction_type":"Sale (Full)","amount_range_low":1001,"amount_range_high":15000,"amount_range_label":"$1,001 - $15,000","comment":null,"is_late":0,"days_to_file":13,"ingested_at":"2026-04-18 18:17:58","row_index":null,"notification_received_over_30d":null,"doc_url":"https://efdsearch.senate.gov/search/view/ptr/bbdeaa6d-dcb6-41fa-a5d5-cb5e5d10af6b/","filing_type":"PTR","ret_since":null,"excess_since":null,"ret_30d":null,"ret_1y":null},{"id":"senate_bbdeaa6d-dcb6-41fa-a5d5-cb5e5d10af6b_t38","filing_id":"senate_bbdeaa6d-dcb6-41fa-a5d5-cb5e5d10af6b","filer_id":"senate_thomasr_tillis","source_id":"senate_efd","transaction_date":"2015-02-13","notification_date":null,"filing_date":"2015-02-26","owner":"Joint","ticker":"OFC","asset_name":"Corporate Office Properties Trust (NYSE)","asset_type":"Stock","transaction_type":"Sale (Full)","amount_range_low":1001,"amount_range_high":15000,"amount_range_label":"$1,001 - $15,000","comment":null,"is_late":0,"days_to_file":13,"ingested_at":"2026-04-18 18:17:58","row_index":null,"notification_received_over_30d":null,"doc_url":"https://efdsearch.senate.gov/search/view/ptr/bbdeaa6d-dcb6-41fa-a5d5-cb5e5d10af6b/","filing_type":"PTR","ret_since":null,"excess_since":null,"ret_30d":null,"ret_1y":null},{"id":"senate_bbdeaa6d-dcb6-41fa-a5d5-cb5e5d10af6b_t39","filing_id":"senate_bbdeaa6d-dcb6-41fa-a5d5-cb5e5d10af6b","filer_id":"senate_thomasr_tillis","source_id":"senate_efd","transaction_date":"2015-02-13","notification_date":null,"filing_date":"2015-02-26","owner":"Joint","ticker":"NSR","asset_name":"NeuStar, Inc. (NYSE)","asset_type":"Stock","transaction_type":"Sale (Full)","amount_range_low":1001,"amount_range_high":15000,"amount_range_label":"$1,001 - $15,000","comment":null,"is_late":0,"days_to_file":13,"ingested_at":"2026-04-18 18:17:58","row_index":null,"notification_received_over_30d":null,"doc_url":"https://efdsearch.senate.gov/search/view/ptr/bbdeaa6d-dcb6-41fa-a5d5-cb5e5d10af6b/","filing_type":"PTR","ret_since":null,"excess_since":null,"ret_30d":null,"ret_1y":null},{"id":"senate_bbdeaa6d-dcb6-41fa-a5d5-cb5e5d10af6b_t40","filing_id":"senate_bbdeaa6d-dcb6-41fa-a5d5-cb5e5d10af6b","filer_id":"senate_thomasr_tillis","source_id":"senate_efd","transaction_date":"2015-02-13","notification_date":null,"filing_date":"2015-02-26","owner":"Joint","ticker":"NICE","asset_name":"NICE Systems Ltd. (NASDAQ)","asset_type":"Stock","transaction_type":"Sale (Full)","amount_range_low":1001,"amount_range_high":15000,"amount_range_label":"$1,001 - $15,000","comment":null,"is_late":0,"days_to_file":13,"ingested_at":"2026-04-18 18:17:58","row_index":null,"notification_received_over_30d":null,"doc_url":"https://efdsearch.senate.gov/search/view/ptr/bbdeaa6d-dcb6-41fa-a5d5-cb5e5d10af6b/","filing_type":"PTR","ret_since":54.85356101878344,"excess_since":-199.98961706302575,"ret_30d":9.596608945686272,"ret_1y":9.099278952666417},{"id":"senate_bbdeaa6d-dcb6-41fa-a5d5-cb5e5d10af6b_t41","filing_id":"senate_bbdeaa6d-dcb6-41fa-a5d5-cb5e5d10af6b","filer_id":"senate_thomasr_tillis","source_id":"senate_efd","transaction_date":"2015-02-13","notification_date":null,"filing_date":"2015-02-26","owner":"Joint","ticker":"MNRO","asset_name":"Monro Muffler Brake Inc. (NASDAQ)","asset_type":"Stock","transaction_type":"Sale (Full)","amount_range_low":1001,"amount_range_high":15000,"amount_range_label":"$1,001 - $15,000","comment":null,"is_late":0,"days_to_file":13,"ingested_at":"2026-04-18 18:17:58","row_index":null,"notification_received_over_30d":null,"doc_url":"https://efdsearch.senate.gov/search/view/ptr/bbdeaa6d-dcb6-41fa-a5d5-cb5e5d10af6b/","filing_type":"PTR","ret_since":null,"excess_since":null,"ret_30d":null,"ret_1y":null},{"id":"senate_bbdeaa6d-dcb6-41fa-a5d5-cb5e5d10af6b_t42","filing_id":"senate_bbdeaa6d-dcb6-41fa-a5d5-cb5e5d10af6b","filer_id":"senate_thomasr_tillis","source_id":"senate_efd","transaction_date":"2015-02-13","notification_date":null,"filing_date":"2015-02-26","owner":"Joint","ticker":"MG","asset_name":"Mistras Group, Inc. (NYSE)","asset_type":"Stock","transaction_type":"Sale (Full)","amount_range_low":1001,"amount_range_high":15000,"amount_range_label":"$1,001 - $15,000","comment":null,"is_late":0,"days_to_file":13,"ingested_at":"2026-04-18 18:17:58","row_index":null,"notification_received_over_30d":null,"doc_url":"https://efdsearch.senate.gov/search/view/ptr/bbdeaa6d-dcb6-41fa-a5d5-cb5e5d10af6b/","filing_type":"PTR","ret_since":null,"excess_since":null,"ret_30d":null,"ret_1y":null},{"id":"senate_bbdeaa6d-dcb6-41fa-a5d5-cb5e5d10af6b_t43","filing_id":"senate_bbdeaa6d-dcb6-41fa-a5d5-cb5e5d10af6b","filer_id":"senate_thomasr_tillis","source_id":"senate_efd","transaction_date":"2015-02-13","notification_date":null,"filing_date":"2015-02-26","owner":"Joint","ticker":"MFRM","asset_name":"Mattress Firm Holding Corp. (NASDAQ)","asset_type":"Stock","transaction_type":"Sale (Full)","amount_range_low":1001,"amount_range_high":15000,"amount_range_label":"$1,001 - $15,000","comment":null,"is_late":0,"days_to_file":13,"ingested_at":"2026-04-18 18:17:58","row_index":null,"notification_received_over_30d":null,"doc_url":"https://efdsearch.senate.gov/search/view/ptr/bbdeaa6d-dcb6-41fa-a5d5-cb5e5d10af6b/","filing_type":"PTR","ret_since":null,"excess_since":null,"ret_30d":null,"ret_1y":null},{"id":"senate_bbdeaa6d-dcb6-41fa-a5d5-cb5e5d10af6b_t44","filing_id":"senate_bbdeaa6d-dcb6-41fa-a5d5-cb5e5d10af6b","filer_id":"senate_thomasr_tillis","source_id":"senate_efd","transaction_date":"2015-02-13","notification_date":null,"filing_date":"2015-02-26","owner":"Joint","ticker":"MDCA","asset_name":"MDC Partners Inc. (NASDAQ)","asset_type":"Stock","transaction_type":"Sale (Full)","amount_range_low":1001,"amount_range_high":15000,"amount_range_label":"$1,001 - $15,000","comment":null,"is_late":0,"days_to_file":13,"ingested_at":"2026-04-18 18:17:58","row_index":null,"notification_received_over_30d":null,"doc_url":"https://efdsearch.senate.gov/search/view/ptr/bbdeaa6d-dcb6-41fa-a5d5-cb5e5d10af6b/","filing_type":"PTR","ret_since":null,"excess_since":null,"ret_30d":null,"ret_1y":null},{"id":"senate_bbdeaa6d-dcb6-41fa-a5d5-cb5e5d10af6b_t45","filing_id":"senate_bbdeaa6d-dcb6-41fa-a5d5-cb5e5d10af6b","filer_id":"senate_thomasr_tillis","source_id":"senate_efd","transaction_date":"2015-02-13","notification_date":null,"filing_date":"2015-02-26","owner":"Joint","ticker":"MASI","asset_name":"Masimo Corporation (NASDAQ)","asset_type":"Stock","transaction_type":"Sale (Full)","amount_range_low":1001,"amount_range_high":15000,"amount_range_label":"$1,001 - $15,000","comment":null,"is_late":0,"days_to_file":13,"ingested_at":"2026-04-18 18:17:58","row_index":null,"notification_received_over_30d":null,"doc_url":"https://efdsearch.senate.gov/search/view/ptr/bbdeaa6d-dcb6-41fa-a5d5-cb5e5d10af6b/","filing_type":"PTR","ret_since":557.2315648792878,"excess_since":303.6468550326773,"ret_30d":15.631851051253554,"ret_1y":33.19942417296267},{"id":"senate_bbdeaa6d-dcb6-41fa-a5d5-cb5e5d10af6b_t46","filing_id":"senate_bbdeaa6d-dcb6-41fa-a5d5-cb5e5d10af6b","filer_id":"senate_thomasr_tillis","source_id":"senate_efd","transaction_date":"2015-02-13","notification_date":null,"filing_date":"2015-02-26","owner":"Joint","ticker":"LSTR","asset_name":"Landstar System Inc. (NASDAQ)","asset_type":"Stock","transaction_type":"Sale (Full)","amount_range_low":1001,"amount_range_high":15000,"amount_range_label":"$1,001 - $15,000","comment":null,"is_late":0,"days_to_file":13,"ingested_at":"2026-04-18 18:17:58","row_index":null,"notification_received_over_30d":null,"doc_url":"https://efdsearch.senate.gov/search/view/ptr/bbdeaa6d-dcb6-41fa-a5d5-cb5e5d10af6b/","filing_type":"PTR","ret_since":204.6050654419017,"excess_since":-50.238112639907484,"ret_30d":0.08743450334055616,"ret_1y":-13.378029368164523},{"id":"senate_bbdeaa6d-dcb6-41fa-a5d5-cb5e5d10af6b_t47","filing_id":"senate_bbdeaa6d-dcb6-41fa-a5d5-cb5e5d10af6b","filer_id":"senate_thomasr_tillis","source_id":"senate_efd","transaction_date":"2015-02-13","notification_date":null,"filing_date":"2015-02-26","owner":"Joint","ticker":"LOCK","asset_name":"LifeLock, Inc. (NYSE)","asset_type":"Stock","transaction_type":"Sale (Full)","amount_range_low":1001,"amount_range_high":15000,"amount_range_label":"$1,001 - $15,000","comment":null,"is_late":0,"days_to_file":13,"ingested_at":"2026-04-18 18:17:58","row_index":null,"notification_received_over_30d":null,"doc_url":"https://efdsearch.senate.gov/search/view/ptr/bbdeaa6d-dcb6-41fa-a5d5-cb5e5d10af6b/","filing_type":"PTR","ret_since":null,"excess_since":null,"ret_30d":null,"ret_1y":null},{"id":"senate_bbdeaa6d-dcb6-41fa-a5d5-cb5e5d10af6b_t48","filing_id":"senate_bbdeaa6d-dcb6-41fa-a5d5-cb5e5d10af6b","filer_id":"senate_thomasr_tillis","source_id":"senate_efd","transaction_date":"2015-02-13","notification_date":null,"filing_date":"2015-02-26","owner":"Joint","ticker":"LL","asset_name":"Lumber Liquidators Holdings, Inc. (NYSE)","asset_type":"Stock","transaction_type":"Sale (Full)","amount_range_low":1001,"amount_range_high":15000,"amount_range_label":"$1,001 - $15,000","comment":null,"is_late":0,"days_to_file":13,"ingested_at":"2026-04-18 18:17:58","row_index":null,"notification_received_over_30d":null,"doc_url":"https://efdsearch.senate.gov/search/view/ptr/bbdeaa6d-dcb6-41fa-a5d5-cb5e5d10af6b/","filing_type":"PTR","ret_since":null,"excess_since":null,"ret_30d":null,"ret_1y":null},{"id":"senate_bbdeaa6d-dcb6-41fa-a5d5-cb5e5d10af6b_t49","filing_id":"senate_bbdeaa6d-dcb6-41fa-a5d5-cb5e5d10af6b","filer_id":"senate_thomasr_tillis","source_id":"senate_efd","transaction_date":"2015-02-13","notification_date":null,"filing_date":"2015-02-26","owner":"Joint","ticker":"KWR","asset_name":"Quaker Chemical Corporation (NYSE)","asset_type":"Stock","transaction_type":"Sale (Full)","amount_range_low":1001,"amount_range_high":15000,"amount_range_label":"$1,001 - $15,000","comment":null,"is_late":0,"days_to_file":13,"ingested_at":"2026-04-18 18:17:58","row_index":null,"notification_received_over_30d":null,"doc_url":"https://efdsearch.senate.gov/search/view/ptr/bbdeaa6d-dcb6-41fa-a5d5-cb5e5d10af6b/","filing_type":"PTR","ret_since":null,"excess_since":null,"ret_30d":null,"ret_1y":null},{"id":"senate_bbdeaa6d-dcb6-41fa-a5d5-cb5e5d10af6b_t50","filing_id":"senate_bbdeaa6d-dcb6-41fa-a5d5-cb5e5d10af6b","filer_id":"senate_thomasr_tillis","source_id":"senate_efd","transaction_date":"2015-02-13","notification_date":null,"filing_date":"2015-02-26","owner":"Joint","ticker":"JJSF","asset_name":"J&J Snack Foods Corp. (NASDAQ)","asset_type":"Stock","transaction_type":"Sale (Full)","amount_range_low":1001,"amount_range_high":15000,"amount_range_label":"$1,001 - $15,000","comment":null,"is_late":0,"days_to_file":13,"ingested_at":"2026-04-18 18:17:58","row_index":null,"notification_received_over_30d":null,"doc_url":"https://efdsearch.senate.gov/search/view/ptr/bbdeaa6d-dcb6-41fa-a5d5-cb5e5d10af6b/","filing_type":"PTR","ret_since":-28.327336086562827,"excess_since":-283.170514168372,"ret_30d":2.4580326133740353,"ret_1y":8.603117958457002},{"id":"senate_bbdeaa6d-dcb6-41fa-a5d5-cb5e5d10af6b_t51","filing_id":"senate_bbdeaa6d-dcb6-41fa-a5d5-cb5e5d10af6b","filer_id":"senate_thomasr_tillis","source_id":"senate_efd","transaction_date":"2015-02-13","notification_date":null,"filing_date":"2015-02-26","owner":"Joint","ticker":"IPCM","asset_name":"IPC Healthcare, Inc. (NASDAQ)","asset_type":"Stock","transaction_type":"Sale (Full)","amount_range_low":1001,"amount_range_high":15000,"amount_range_label":"$1,001 - $15,000","comment":null,"is_late":0,"days_to_file":13,"ingested_at":"2026-04-18 18:17:58","row_index":null,"notification_received_over_30d":null,"doc_url":"https://efdsearch.senate.gov/search/view/ptr/bbdeaa6d-dcb6-41fa-a5d5-cb5e5d10af6b/","filing_type":"PTR","ret_since":null,"excess_since":null,"ret_30d":null,"ret_1y":null},{"id":"senate_bbdeaa6d-dcb6-41fa-a5d5-cb5e5d10af6b_t52","filing_id":"senate_bbdeaa6d-dcb6-41fa-a5d5-cb5e5d10af6b","filer_id":"senate_thomasr_tillis","source_id":"senate_efd","transaction_date":"2015-02-13","notification_date":null,"filing_date":"2015-02-26","owner":"Joint","ticker":"ICUI","asset_name":"ICU Medical, Inc. (NASDAQ)","asset_type":"Stock","transaction_type":"Sale (Full)","amount_range_low":1001,"amount_range_high":15000,"amount_range_label":"$1,001 - $15,000","comment":null,"is_late":0,"days_to_file":13,"ingested_at":"2026-04-18 18:17:58","row_index":null,"notification_received_over_30d":null,"doc_url":"https://efdsearch.senate.gov/search/view/ptr/bbdeaa6d-dcb6-41fa-a5d5-cb5e5d10af6b/","filing_type":"PTR","ret_since":53.0006678506604,"excess_since":-201.8425102311488,"ret_30d":2.8658072894583433,"ret_1y":0},{"id":"senate_bbdeaa6d-dcb6-41fa-a5d5-cb5e5d10af6b_t53","filing_id":"senate_bbdeaa6d-dcb6-41fa-a5d5-cb5e5d10af6b","filer_id":"senate_thomasr_tillis","source_id":"senate_efd","transaction_date":"2015-02-13","notification_date":null,"filing_date":"2015-02-26","owner":"Joint","ticker":"ICON","asset_name":"Iconix Brand Group, Inc. (NASDAQ)","asset_type":"Stock","transaction_type":"Sale (Full)","amount_range_low":1001,"amount_range_high":15000,"amount_range_label":"$1,001 - $15,000","comment":null,"is_late":0,"days_to_file":13,"ingested_at":"2026-04-18 18:17:58","row_index":null,"notification_received_over_30d":null,"doc_url":"https://efdsearch.senate.gov/search/view/ptr/bbdeaa6d-dcb6-41fa-a5d5-cb5e5d10af6b/","filing_type":"PTR","ret_since":null,"excess_since":null,"ret_30d":null,"ret_1y":null},{"id":"senate_bbdeaa6d-dcb6-41fa-a5d5-cb5e5d10af6b_t54","filing_id":"senate_bbdeaa6d-dcb6-41fa-a5d5-cb5e5d10af6b","filer_id":"senate_thomasr_tillis","source_id":"senate_efd","transaction_date":"2015-02-13","notification_date":null,"filing_date":"2015-02-26","owner":"Joint","ticker":"HUBG","asset_name":"Hub Group Inc. (NASDAQ)","asset_type":"Stock","transaction_type":"Sale (Full)","amount_range_low":1001,"amount_range_high":15000,"amount_range_label":"$1,001 - $15,000","comment":null,"is_late":0,"days_to_file":13,"ingested_at":"2026-04-18 18:17:58","row_index":null,"notification_received_over_30d":null,"doc_url":"https://efdsearch.senate.gov/search/view/ptr/bbdeaa6d-dcb6-41fa-a5d5-cb5e5d10af6b/","filing_type":"PTR","ret_since":null,"excess_since":null,"ret_30d":null,"ret_1y":null},{"id":"senate_bbdeaa6d-dcb6-41fa-a5d5-cb5e5d10af6b_t55","filing_id":"senate_bbdeaa6d-dcb6-41fa-a5d5-cb5e5d10af6b","filer_id":"senate_thomasr_tillis","source_id":"senate_efd","transaction_date":"2015-02-13","notification_date":null,"filing_date":"2015-02-26","owner":"Joint","ticker":"IART","asset_name":"Integra LifeSciences Holdings Corporation (NASDAQ)","asset_type":"Stock","transaction_type":"Sale (Full)","amount_range_low":1001,"amount_range_high":15000,"amount_range_label":"$1,001 - $15,000","comment":null,"is_late":0,"days_to_file":13,"ingested_at":"2026-04-18 18:17:58","row_index":null,"notification_received_over_30d":null,"doc_url":"https://efdsearch.senate.gov/search/view/ptr/bbdeaa6d-dcb6-41fa-a5d5-cb5e5d10af6b/","filing_type":"PTR","ret_since":-31.567586977870615,"excess_since":-286.4107650596798,"ret_30d":5.220600439244494,"ret_1y":11.222107996833595},{"id":"senate_bbdeaa6d-dcb6-41fa-a5d5-cb5e5d10af6b_t56","filing_id":"senate_bbdeaa6d-dcb6-41fa-a5d5-cb5e5d10af6b","filer_id":"senate_thomasr_tillis","source_id":"senate_efd","transaction_date":"2015-02-13","notification_date":null,"filing_date":"2015-02-26","owner":"Joint","ticker":"HLX","asset_name":"Helix Energy Solutions Group, Inc. (NYSE)","asset_type":"Stock","transaction_type":"Sale (Full)","amount_range_low":1001,"amount_range_high":15000,"amount_range_label":"$1,001 - $15,000","comment":null,"is_late":0,"days_to_file":13,"ingested_at":"2026-04-18 18:17:58","row_index":null,"notification_received_over_30d":null,"doc_url":"https://efdsearch.senate.gov/search/view/ptr/bbdeaa6d-dcb6-41fa-a5d5-cb5e5d10af6b/","filing_type":"PTR","ret_since":-53.61635001646937,"excess_since":-308.45952809827855,"ret_30d":-28.98322722790167,"ret_1y":-84.17190779348851},{"id":"senate_bbdeaa6d-dcb6-41fa-a5d5-cb5e5d10af6b_t57","filing_id":"senate_bbdeaa6d-dcb6-41fa-a5d5-cb5e5d10af6b","filer_id":"senate_thomasr_tillis","source_id":"senate_efd","transaction_date":"2015-02-13","notification_date":null,"filing_date":"2015-02-26","owner":"Joint","ticker":"HF","asset_name":"HFF, Inc. (NYSE)","asset_type":"Stock","transaction_type":"Sale (Full)","amount_range_low":1001,"amount_range_high":15000,"amount_range_label":"$1,001 - $15,000","comment":null,"is_late":0,"days_to_file":13,"ingested_at":"2026-04-18 18:17:58","row_index":null,"notification_received_over_30d":null,"doc_url":"https://efdsearch.senate.gov/search/view/ptr/bbdeaa6d-dcb6-41fa-a5d5-cb5e5d10af6b/","filing_type":"PTR","ret_since":null,"excess_since":null,"ret_30d":null,"ret_1y":null},{"id":"senate_bbdeaa6d-dcb6-41fa-a5d5-cb5e5d10af6b_t58","filing_id":"senate_bbdeaa6d-dcb6-41fa-a5d5-cb5e5d10af6b","filer_id":"senate_thomasr_tillis","source_id":"senate_efd","transaction_date":"2015-02-13","notification_date":null,"filing_date":"2015-02-26","owner":"Joint","ticker":"HEI","asset_name":"HEICO Corporation (NYSE)","asset_type":"Stock","transaction_type":"Sale (Full)","amount_range_low":1001,"amount_range_high":15000,"amount_range_label":"$1,001 - $15,000","comment":null,"is_late":0,"days_to_file":13,"ingested_at":"2026-04-18 18:17:58","row_index":null,"notification_received_over_30d":null,"doc_url":"https://efdsearch.senate.gov/search/view/ptr/bbdeaa6d-dcb6-41fa-a5d5-cb5e5d10af6b/","filing_type":"PTR","ret_since":934.8437309265137,"excess_since":680.0005528447045,"ret_30d":-3.9839982986450195,"ret_1y":-14.928001165390015},{"id":"senate_bbdeaa6d-dcb6-41fa-a5d5-cb5e5d10af6b_t59","filing_id":"senate_bbdeaa6d-dcb6-41fa-a5d5-cb5e5d10af6b","filer_id":"senate_thomasr_tillis","source_id":"senate_efd","transaction_date":"2015-02-13","notification_date":null,"filing_date":"2015-02-26","owner":"Joint","ticker":"HCSG","asset_name":"Healthcare Services Group Inc. (NASDAQ)","asset_type":"Stock","transaction_type":"Sale (Full)","amount_range_low":1001,"amount_range_high":15000,"amount_range_label":"$1,001 - $15,000","comment":null,"is_late":0,"days_to_file":13,"ingested_at":"2026-04-18 18:17:58","row_index":null,"notification_received_over_30d":null,"doc_url":"https://efdsearch.senate.gov/search/view/ptr/bbdeaa6d-dcb6-41fa-a5d5-cb5e5d10af6b/","filing_type":"PTR","ret_since":-32.16972246154164,"excess_since":-287.01290054335084,"ret_30d":-0.812520197060169,"ret_1y":5.055673573032856},{"id":"senate_bbdeaa6d-dcb6-41fa-a5d5-cb5e5d10af6b_t60","filing_id":"senate_bbdeaa6d-dcb6-41fa-a5d5-cb5e5d10af6b","filer_id":"senate_thomasr_tillis","source_id":"senate_efd","transaction_date":"2015-02-13","notification_date":null,"filing_date":"2015-02-26","owner":"Joint","ticker":"GMED","asset_name":"Globus Medical, Inc. (NYSE)","asset_type":"Stock","transaction_type":"Sale (Full)","amount_range_low":1001,"amount_range_high":15000,"amount_range_label":"$1,001 - $15,000","comment":null,"is_late":0,"days_to_file":13,"ingested_at":"2026-04-18 18:17:58","row_index":null,"notification_received_over_30d":null,"doc_url":"https://efdsearch.senate.gov/search/view/ptr/bbdeaa6d-dcb6-41fa-a5d5-cb5e5d10af6b/","filing_type":"PTR","ret_since":218.6720371258306,"excess_since":-36.171140955978586,"ret_30d":-0.20121184564031153,"ret_1y":-7.122738151277996},{"id":"senate_bbdeaa6d-dcb6-41fa-a5d5-cb5e5d10af6b_t61","filing_id":"senate_bbdeaa6d-dcb6-41fa-a5d5-cb5e5d10af6b","filer_id":"senate_thomasr_tillis","source_id":"senate_efd","transaction_date":"2015-02-13","notification_date":null,"filing_date":"2015-02-26","owner":"Joint","ticker":"FNGN","asset_name":"Financial Engines, Inc. (NASDAQ)","asset_type":"Stock","transaction_type":"Sale (Full)","amount_range_low":1001,"amount_range_high":15000,"amount_range_label":"$1,001 - $15,000","comment":null,"is_late":0,"days_to_file":13,"ingested_at":"2026-04-18 18:17:58","row_index":null,"notification_received_over_30d":null,"doc_url":"https://efdsearch.senate.gov/search/view/ptr/bbdeaa6d-dcb6-41fa-a5d5-cb5e5d10af6b/","filing_type":"PTR","ret_since":null,"excess_since":null,"ret_30d":null,"ret_1y":null},{"id":"senate_bbdeaa6d-dcb6-41fa-a5d5-cb5e5d10af6b_t62","filing_id":"senate_bbdeaa6d-dcb6-41fa-a5d5-cb5e5d10af6b","filer_id":"senate_thomasr_tillis","source_id":"senate_efd","transaction_date":"2015-02-13","notification_date":null,"filing_date":"2015-02-26","owner":"Joint","ticker":"FMBI","asset_name":"First Midwest Bancorp Inc. (NASDAQ)","asset_type":"Stock","transaction_type":"Sale (Full)","amount_range_low":1001,"amount_range_high":15000,"amount_range_label":"$1,001 - $15,000","comment":null,"is_late":0,"days_to_file":13,"ingested_at":"2026-04-18 18:17:58","row_index":null,"notification_received_over_30d":null,"doc_url":"https://efdsearch.senate.gov/search/view/ptr/bbdeaa6d-dcb6-41fa-a5d5-cb5e5d10af6b/","filing_type":"PTR","ret_since":null,"excess_since":null,"ret_30d":null,"ret_1y":null},{"id":"senate_bbdeaa6d-dcb6-41fa-a5d5-cb5e5d10af6b_t63","filing_id":"senate_bbdeaa6d-dcb6-41fa-a5d5-cb5e5d10af6b","filer_id":"senate_thomasr_tillis","source_id":"senate_efd","transaction_date":"2015-02-13","notification_date":null,"filing_date":"2015-02-26","owner":"Joint","ticker":"FET","asset_name":"Forum Energy Technologies, Inc. (NYSE)","asset_type":"Stock","transaction_type":"Sale (Full)","amount_range_low":1001,"amount_range_high":15000,"amount_range_label":"$1,001 - $15,000","comment":null,"is_late":0,"days_to_file":13,"ingested_at":"2026-04-18 18:17:58","row_index":null,"notification_received_over_30d":null,"doc_url":"https://efdsearch.senate.gov/search/view/ptr/bbdeaa6d-dcb6-41fa-a5d5-cb5e5d10af6b/","filing_type":"PTR","ret_since":-86.2754005799319,"excess_since":-341.1185786617411,"ret_30d":-1.06951871657754,"ret_1y":-51.33689839572193},{"id":"senate_bbdeaa6d-dcb6-41fa-a5d5-cb5e5d10af6b_t64","filing_id":"senate_bbdeaa6d-dcb6-41fa-a5d5-cb5e5d10af6b","filer_id":"senate_thomasr_tillis","source_id":"senate_efd","transaction_date":"2015-02-13","notification_date":null,"filing_date":"2015-02-26","owner":"Joint","ticker":"EVR","asset_name":"Evercore Partners Inc. (NYSE)","asset_type":"Stock","transaction_type":"Sale (Full)","amount_range_low":1001,"amount_range_high":15000,"amount_range_label":"$1,001 - $15,000","comment":null,"is_late":0,"days_to_file":13,"ingested_at":"2026-04-18 18:17:58","row_index":null,"notification_received_over_30d":null,"doc_url":"https://efdsearch.senate.gov/search/view/ptr/bbdeaa6d-dcb6-41fa-a5d5-cb5e5d10af6b/","filing_type":"PTR","ret_since":null,"excess_since":null,"ret_30d":null,"ret_1y":null},{"id":"senate_bbdeaa6d-dcb6-41fa-a5d5-cb5e5d10af6b_t65","filing_id":"senate_bbdeaa6d-dcb6-41fa-a5d5-cb5e5d10af6b","filer_id":"senate_thomasr_tillis","source_id":"senate_efd","transaction_date":"2015-02-13","notification_date":null,"filing_date":"2015-02-26","owner":"Joint","ticker":"EPAY","asset_name":"Bottomline Technologies (de), Inc. (NASDAQ)","asset_type":"Stock","transaction_type":"Sale (Full)","amount_range_low":1001,"amount_range_high":15000,"amount_range_label":"$1,001 - $15,000","comment":null,"is_late":0,"days_to_file":13,"ingested_at":"2026-04-18 18:17:58","row_index":null,"notification_received_over_30d":null,"doc_url":"https://efdsearch.senate.gov/search/view/ptr/bbdeaa6d-dcb6-41fa-a5d5-cb5e5d10af6b/","filing_type":"PTR","ret_since":null,"excess_since":null,"ret_30d":null,"ret_1y":null},{"id":"senate_bbdeaa6d-dcb6-41fa-a5d5-cb5e5d10af6b_t66","filing_id":"senate_bbdeaa6d-dcb6-41fa-a5d5-cb5e5d10af6b","filer_id":"senate_thomasr_tillis","source_id":"senate_efd","transaction_date":"2015-02-13","notification_date":null,"filing_date":"2015-02-26","owner":"Joint","ticker":"EGBN","asset_name":"Eagle Bancorp, Inc. (NASDAQ)","asset_type":"Stock","transaction_type":"Sale (Full)","amount_range_low":1001,"amount_range_high":15000,"amount_range_label":"$1,001 - $15,000","comment":null,"is_late":0,"days_to_file":13,"ingested_at":"2026-04-18 18:17:58","row_index":null,"notification_received_over_30d":null,"doc_url":"https://efdsearch.senate.gov/search/view/ptr/bbdeaa6d-dcb6-41fa-a5d5-cb5e5d10af6b/","filing_type":"PTR","ret_since":null,"excess_since":null,"ret_30d":null,"ret_1y":null},{"id":"senate_bbdeaa6d-dcb6-41fa-a5d5-cb5e5d10af6b_t67","filing_id":"senate_bbdeaa6d-dcb6-41fa-a5d5-cb5e5d10af6b","filer_id":"senate_thomasr_tillis","source_id":"senate_efd","transaction_date":"2015-02-13","notification_date":null,"filing_date":"2015-02-26","owner":"Joint","ticker":"DRQ","asset_name":"Dril-Quip, Inc. (NYSE)","asset_type":"Stock","transaction_type":"Sale (Full)","amount_range_low":1001,"amount_range_high":15000,"amount_range_label":"$1,001 - $15,000","comment":null,"is_late":0,"days_to_file":13,"ingested_at":"2026-04-18 18:17:58","row_index":null,"notification_received_over_30d":null,"doc_url":"https://efdsearch.senate.gov/search/view/ptr/bbdeaa6d-dcb6-41fa-a5d5-cb5e5d10af6b/","filing_type":"PTR","ret_since":null,"excess_since":null,"ret_30d":null,"ret_1y":null},{"id":"senate_bbdeaa6d-dcb6-41fa-a5d5-cb5e5d10af6b_t68","filing_id":"senate_bbdeaa6d-dcb6-41fa-a5d5-cb5e5d10af6b","filer_id":"senate_thomasr_tillis","source_id":"senate_efd","transaction_date":"2015-02-13","notification_date":null,"filing_date":"2015-02-26","owner":"Joint","ticker":"DIOD","asset_name":"Diodes Incorporated (NASDAQ)","asset_type":"Stock","transaction_type":"Sale (Full)","amount_range_low":1001,"amount_range_high":15000,"amount_range_label":"$1,001 - $15,000","comment":null,"is_late":0,"days_to_file":13,"ingested_at":"2026-04-18 18:17:58","row_index":null,"notification_received_over_30d":null,"doc_url":"https://efdsearch.senate.gov/search/view/ptr/bbdeaa6d-dcb6-41fa-a5d5-cb5e5d10af6b/","filing_type":"PTR","ret_since":341.42396437860043,"excess_since":86.58078629679125,"ret_30d":6.939950889029549,"ret_1y":-33.22545828321199},{"id":"senate_bbdeaa6d-dcb6-41fa-a5d5-cb5e5d10af6b_t69","filing_id":"senate_bbdeaa6d-dcb6-41fa-a5d5-cb5e5d10af6b","filer_id":"senate_thomasr_tillis","source_id":"senate_efd","transaction_date":"2015-02-13","notification_date":null,"filing_date":"2015-02-26","owner":"Joint","ticker":"DFRG","asset_name":"Del Frisco's Restaurant Group, Inc. (NASDAQ)","asset_type":"Stock","transaction_type":"Sale (Full)","amount_range_low":1001,"amount_range_high":15000,"amount_range_label":"$1,001 - $15,000","comment":null,"is_late":0,"days_to_file":13,"ingested_at":"2026-04-18 18:17:58","row_index":null,"notification_received_over_30d":null,"doc_url":"https://efdsearch.senate.gov/search/view/ptr/bbdeaa6d-dcb6-41fa-a5d5-cb5e5d10af6b/","filing_type":"PTR","ret_since":null,"excess_since":null,"ret_30d":null,"ret_1y":null},{"id":"senate_bbdeaa6d-dcb6-41fa-a5d5-cb5e5d10af6b_t70","filing_id":"senate_bbdeaa6d-dcb6-41fa-a5d5-cb5e5d10af6b","filer_id":"senate_thomasr_tillis","source_id":"senate_efd","transaction_date":"2015-02-13","notification_date":null,"filing_date":"2015-02-26","owner":"Joint","ticker":"CYBX","asset_name":"Cyberonics Inc. (NASDAQ)","asset_type":"Stock","transaction_type":"Sale (Full)","amount_range_low":1001,"amount_range_high":15000,"amount_range_label":"$1,001 - $15,000","comment":null,"is_late":0,"days_to_file":13,"ingested_at":"2026-04-18 18:17:58","row_index":null,"notification_received_over_30d":null,"doc_url":"https://efdsearch.senate.gov/search/view/ptr/bbdeaa6d-dcb6-41fa-a5d5-cb5e5d10af6b/","filing_type":"PTR","ret_since":null,"excess_since":null,"ret_30d":null,"ret_1y":null},{"id":"senate_bbdeaa6d-dcb6-41fa-a5d5-cb5e5d10af6b_t71","filing_id":"senate_bbdeaa6d-dcb6-41fa-a5d5-cb5e5d10af6b","filer_id":"senate_thomasr_tillis","source_id":"senate_efd","transaction_date":"2015-02-13","notification_date":null,"filing_date":"2015-02-26","owner":"Joint","ticker":"CVLT","asset_name":"CommVault Systems, Inc. (NASDAQ)","asset_type":"Stock","transaction_type":"Sale (Full)","amount_range_low":1001,"amount_range_high":15000,"amount_range_label":"$1,001 - $15,000","comment":null,"is_late":0,"days_to_file":13,"ingested_at":"2026-04-18 18:17:58","row_index":null,"notification_received_over_30d":null,"doc_url":"https://efdsearch.senate.gov/search/view/ptr/bbdeaa6d-dcb6-41fa-a5d5-cb5e5d10af6b/","filing_type":"PTR","ret_since":188.48443510953717,"excess_since":-66.35874297227201,"ret_30d":5.1968874585714975,"ret_1y":-17.765572532083894},{"id":"senate_bbdeaa6d-dcb6-41fa-a5d5-cb5e5d10af6b_t72","filing_id":"senate_bbdeaa6d-dcb6-41fa-a5d5-cb5e5d10af6b","filer_id":"senate_thomasr_tillis","source_id":"senate_efd","transaction_date":"2015-02-13","notification_date":null,"filing_date":"2015-02-26","owner":"Joint","ticker":"CTRL","asset_name":"Control4 Corporation (NASDAQ)","asset_type":"Stock","transaction_type":"Sale (Full)","amount_range_low":1001,"amount_range_high":15000,"amount_range_label":"$1,001 - $15,000","comment":null,"is_late":0,"days_to_file":13,"ingested_at":"2026-04-18 18:17:58","row_index":null,"notification_received_over_30d":null,"doc_url":"https://efdsearch.senate.gov/search/view/ptr/bbdeaa6d-dcb6-41fa-a5d5-cb5e5d10af6b/","filing_type":"PTR","ret_since":null,"excess_since":null,"ret_30d":null,"ret_1y":null},{"id":"senate_bbdeaa6d-dcb6-41fa-a5d5-cb5e5d10af6b_t73","filing_id":"senate_bbdeaa6d-dcb6-41fa-a5d5-cb5e5d10af6b","filer_id":"senate_thomasr_tillis","source_id":"senate_efd","transaction_date":"2015-02-13","notification_date":null,"filing_date":"2015-02-26","owner":"Joint","ticker":"CTCT","asset_name":"Constant Contact, Inc. (NASDAQ)","asset_type":"Stock","transaction_type":"Sale (Full)","amount_range_low":1001,"amount_range_high":15000,"amount_range_label":"$1,001 - $15,000","comment":null,"is_late":0,"days_to_file":13,"ingested_at":"2026-04-18 18:17:58","row_index":null,"notification_received_over_30d":null,"doc_url":"https://efdsearch.senate.gov/search/view/ptr/bbdeaa6d-dcb6-41fa-a5d5-cb5e5d10af6b/","filing_type":"PTR","ret_since":null,"excess_since":null,"ret_30d":null,"ret_1y":null},{"id":"senate_bbdeaa6d-dcb6-41fa-a5d5-cb5e5d10af6b_t74","filing_id":"senate_bbdeaa6d-dcb6-41fa-a5d5-cb5e5d10af6b","filer_id":"senate_thomasr_tillis","source_id":"senate_efd","transaction_date":"2015-02-13","notification_date":null,"filing_date":"2015-02-26","owner":"Joint","ticker":"CRZO","asset_name":"Carrizo Oil & Gas Inc. (NASDAQ)","asset_type":"Stock","transaction_type":"Sale (Full)","amount_range_low":1001,"amount_range_high":15000,"amount_range_label":"$1,001 - $15,000","comment":null,"is_late":0,"days_to_file":13,"ingested_at":"2026-04-18 18:17:58","row_index":null,"notification_received_over_30d":null,"doc_url":"https://efdsearch.senate.gov/search/view/ptr/bbdeaa6d-dcb6-41fa-a5d5-cb5e5d10af6b/","filing_type":"PTR","ret_since":null,"excess_since":null,"ret_30d":null,"ret_1y":null},{"id":"senate_bbdeaa6d-dcb6-41fa-a5d5-cb5e5d10af6b_t75","filing_id":"senate_bbdeaa6d-dcb6-41fa-a5d5-cb5e5d10af6b","filer_id":"senate_thomasr_tillis","source_id":"senate_efd","transaction_date":"2015-02-13","notification_date":null,"filing_date":"2015-02-26","owner":"Joint","ticker":"CMN","asset_name":"Cantel Medical Corp. (NYSE)","asset_type":"Stock","transaction_type":"Sale (Full)","amount_range_low":1001,"amount_range_high":15000,"amount_range_label":"$1,001 - $15,000","comment":null,"is_late":0,"days_to_file":13,"ingested_at":"2026-04-18 18:17:58","row_index":null,"notification_received_over_30d":null,"doc_url":"https://efdsearch.senate.gov/search/view/ptr/bbdeaa6d-dcb6-41fa-a5d5-cb5e5d10af6b/","filing_type":"PTR","ret_since":null,"excess_since":null,"ret_30d":null,"ret_1y":null},{"id":"senate_bbdeaa6d-dcb6-41fa-a5d5-cb5e5d10af6b_t76","filing_id":"senate_bbdeaa6d-dcb6-41fa-a5d5-cb5e5d10af6b","filer_id":"senate_thomasr_tillis","source_id":"senate_efd","transaction_date":"2015-02-13","notification_date":null,"filing_date":"2015-02-26","owner":"Joint","ticker":"CLC","asset_name":"CLARCOR Inc. (NYSE)","asset_type":"Stock","transaction_type":"Sale (Full)","amount_range_low":1001,"amount_range_high":15000,"amount_range_label":"$1,001 - $15,000","comment":null,"is_late":0,"days_to_file":13,"ingested_at":"2026-04-18 18:17:58","row_index":null,"notification_received_over_30d":null,"doc_url":"https://efdsearch.senate.gov/search/view/ptr/bbdeaa6d-dcb6-41fa-a5d5-cb5e5d10af6b/","filing_type":"PTR","ret_since":null,"excess_since":null,"ret_30d":null,"ret_1y":null},{"id":"senate_bbdeaa6d-dcb6-41fa-a5d5-cb5e5d10af6b_t77","filing_id":"senate_bbdeaa6d-dcb6-41fa-a5d5-cb5e5d10af6b","filer_id":"senate_thomasr_tillis","source_id":"senate_efd","transaction_date":"2015-02-13","notification_date":null,"filing_date":"2015-02-26","owner":"Joint","ticker":"CHEF","asset_name":"The Chefs' Warehouse, Inc. (NASDAQ)","asset_type":"Stock","transaction_type":"Sale (Full)","amount_range_low":1001,"amount_range_high":15000,"amount_range_label":"$1,001 - $15,000","comment":null,"is_late":0,"days_to_file":13,"ingested_at":"2026-04-18 18:17:58","row_index":null,"notification_received_over_30d":null,"doc_url":"https://efdsearch.senate.gov/search/view/ptr/bbdeaa6d-dcb6-41fa-a5d5-cb5e5d10af6b/","filing_type":"PTR","ret_since":null,"excess_since":null,"ret_30d":null,"ret_1y":null},{"id":"senate_bbdeaa6d-dcb6-41fa-a5d5-cb5e5d10af6b_t78","filing_id":"senate_bbdeaa6d-dcb6-41fa-a5d5-cb5e5d10af6b","filer_id":"senate_thomasr_tillis","source_id":"senate_efd","transaction_date":"2015-02-13","notification_date":null,"filing_date":"2015-02-26","owner":"Joint","ticker":"CGNX","asset_name":"Cognex Corporation (NASDAQ)","asset_type":"Stock","transaction_type":"Sale (Full)","amount_range_low":1001,"amount_range_high":15000,"amount_range_label":"$1,001 - $15,000","comment":null,"is_late":0,"days_to_file":13,"ingested_at":"2026-04-18 18:17:58","row_index":null,"notification_received_over_30d":null,"doc_url":"https://efdsearch.senate.gov/search/view/ptr/bbdeaa6d-dcb6-41fa-a5d5-cb5e5d10af6b/","filing_type":"PTR","ret_since":223.29028678824926,"excess_since":-31.552891293559924,"ret_30d":18.60353619337724,"ret_1y":-17.431853105512047},{"id":"senate_bbdeaa6d-dcb6-41fa-a5d5-cb5e5d10af6b_t79","filing_id":"senate_bbdeaa6d-dcb6-41fa-a5d5-cb5e5d10af6b","filer_id":"senate_thomasr_tillis","source_id":"senate_efd","transaction_date":"2015-02-13","notification_date":null,"filing_date":"2015-02-26","owner":"Joint","ticker":"CASY","asset_name":"Casey's General Stores, Inc. (NASDAQ)","asset_type":"Stock","transaction_type":"Sale (Full)","amount_range_low":1001,"amount_range_high":15000,"amount_range_label":"$1,001 - $15,000","comment":null,"is_late":0,"days_to_file":13,"ingested_at":"2026-04-18 18:17:58","row_index":null,"notification_received_over_30d":null,"doc_url":"https://efdsearch.senate.gov/search/view/ptr/bbdeaa6d-dcb6-41fa-a5d5-cb5e5d10af6b/","filing_type":"PTR","ret_since":835.1961993209985,"excess_since":580.3530212391893,"ret_30d":-0.9783006225081464,"ret_1y":31.37299160028802},{"id":"senate_bbdeaa6d-dcb6-41fa-a5d5-cb5e5d10af6b_t80","filing_id":"senate_bbdeaa6d-dcb6-41fa-a5d5-cb5e5d10af6b","filer_id":"senate_thomasr_tillis","source_id":"senate_efd","transaction_date":"2015-02-13","notification_date":null,"filing_date":"2015-02-26","owner":"Joint","ticker":"BMR","asset_name":"BioMed Realty Trust Inc. (NYSE)","asset_type":"Stock","transaction_type":"Sale (Full)","amount_range_low":1001,"amount_range_high":15000,"amount_range_label":"$1,001 - $15,000","comment":null,"is_late":0,"days_to_file":13,"ingested_at":"2026-04-18 18:17:58","row_index":null,"notification_received_over_30d":null,"doc_url":"https://efdsearch.senate.gov/search/view/ptr/bbdeaa6d-dcb6-41fa-a5d5-cb5e5d10af6b/","filing_type":"PTR","ret_since":null,"excess_since":null,"ret_30d":null,"ret_1y":null},{"id":"senate_bbdeaa6d-dcb6-41fa-a5d5-cb5e5d10af6b_t81","filing_id":"senate_bbdeaa6d-dcb6-41fa-a5d5-cb5e5d10af6b","filer_id":"senate_thomasr_tillis","source_id":"senate_efd","transaction_date":"2015-02-13","notification_date":null,"filing_date":"2015-02-26","owner":"Joint","ticker":"BIO","asset_name":"Bio-Rad Laboratories, Inc. (NYSE)","asset_type":"Stock","transaction_type":"Sale (Full)","amount_range_low":1001,"amount_range_high":15000,"amount_range_label":"$1,001 - $15,000","comment":null,"is_late":0,"days_to_file":13,"ingested_at":"2026-04-18 18:17:58","row_index":null,"notification_received_over_30d":null,"doc_url":"https://efdsearch.senate.gov/search/view/ptr/bbdeaa6d-dcb6-41fa-a5d5-cb5e5d10af6b/","filing_type":"PTR","ret_since":137.50421079921583,"excess_since":-117.33896728259336,"ret_30d":14.962830874063297,"ret_1y":7.60392020411402},{"id":"senate_bbdeaa6d-dcb6-41fa-a5d5-cb5e5d10af6b_t82","filing_id":"senate_bbdeaa6d-dcb6-41fa-a5d5-cb5e5d10af6b","filer_id":"senate_thomasr_tillis","source_id":"senate_efd","transaction_date":"2015-02-13","notification_date":null,"filing_date":"2015-02-26","owner":"Joint","ticker":"BERY","asset_name":"Berry Plastics Group, Inc. (NYSE)","asset_type":"Stock","transaction_type":"Sale (Full)","amount_range_low":1001,"amount_range_high":15000,"amount_range_label":"$1,001 - $15,000","comment":null,"is_late":0,"days_to_file":13,"ingested_at":"2026-04-18 18:17:58","row_index":null,"notification_received_over_30d":null,"doc_url":"https://efdsearch.senate.gov/search/view/ptr/bbdeaa6d-dcb6-41fa-a5d5-cb5e5d10af6b/","filing_type":"PTR","ret_since":null,"excess_since":null,"ret_30d":null,"ret_1y":null},{"id":"senate_bbdeaa6d-dcb6-41fa-a5d5-cb5e5d10af6b_t83","filing_id":"senate_bbdeaa6d-dcb6-41fa-a5d5-cb5e5d10af6b","filer_id":"senate_thomasr_tillis","source_id":"senate_efd","transaction_date":"2015-02-13","notification_date":null,"filing_date":"2015-02-26","owner":"Joint","ticker":"BECN","asset_name":"Beacon Roofing Supply, Inc. (NASDAQ)","asset_type":"Stock","transaction_type":"Sale (Full)","amount_range_low":1001,"amount_range_high":15000,"amount_range_label":"$1,001 - $15,000","comment":null,"is_late":0,"days_to_file":13,"ingested_at":"2026-04-18 18:17:58","row_index":null,"notification_received_over_30d":null,"doc_url":"https://efdsearch.senate.gov/search/view/ptr/bbdeaa6d-dcb6-41fa-a5d5-cb5e5d10af6b/","filing_type":"PTR","ret_since":null,"excess_since":null,"ret_30d":null,"ret_1y":null},{"id":"senate_bbdeaa6d-dcb6-41fa-a5d5-cb5e5d10af6b_t84","filing_id":"senate_bbdeaa6d-dcb6-41fa-a5d5-cb5e5d10af6b","filer_id":"senate_thomasr_tillis","source_id":"senate_efd","transaction_date":"2015-02-13","notification_date":null,"filing_date":"2015-02-26","owner":"Joint","ticker":"BCPC","asset_name":"Balchem Corp. (NASDAQ)","asset_type":"Stock","transaction_type":"Sale (Full)","amount_range_low":1001,"amount_range_high":15000,"amount_range_label":"$1,001 - $15,000","comment":null,"is_late":0,"days_to_file":13,"ingested_at":"2026-04-18 18:17:58","row_index":null,"notification_received_over_30d":null,"doc_url":"https://efdsearch.senate.gov/search/view/ptr/bbdeaa6d-dcb6-41fa-a5d5-cb5e5d10af6b/","filing_type":"PTR","ret_since":184.58234179398823,"excess_since":-70.26083628782095,"ret_30d":-3.403230546322607,"ret_1y":10.519083386868918},{"id":"senate_bbdeaa6d-dcb6-41fa-a5d5-cb5e5d10af6b_t85","filing_id":"senate_bbdeaa6d-dcb6-41fa-a5d5-cb5e5d10af6b","filer_id":"senate_thomasr_tillis","source_id":"senate_efd","transaction_date":"2015-02-13","notification_date":null,"filing_date":"2015-02-26","owner":"Joint","ticker":"ATRO","asset_name":"Astronics Corporation (NASDAQ)","asset_type":"Stock","transaction_type":"Sale (Full)","amount_range_low":1001,"amount_range_high":15000,"amount_range_label":"$1,001 - $15,000","comment":null,"is_late":0,"days_to_file":13,"ingested_at":"2026-04-18 18:17:58","row_index":null,"notification_received_over_30d":null,"doc_url":"https://efdsearch.senate.gov/search/view/ptr/bbdeaa6d-dcb6-41fa-a5d5-cb5e5d10af6b/","filing_type":"PTR","ret_since":null,"excess_since":null,"ret_30d":null,"ret_1y":null},{"id":"senate_bbdeaa6d-dcb6-41fa-a5d5-cb5e5d10af6b_t86","filing_id":"senate_bbdeaa6d-dcb6-41fa-a5d5-cb5e5d10af6b","filer_id":"senate_thomasr_tillis","source_id":"senate_efd","transaction_date":"2015-02-13","notification_date":null,"filing_date":"2015-02-26","owner":"Joint","ticker":"AMSG","asset_name":"AmSurg Corp. (NASDAQ)","asset_type":"Stock","transaction_type":"Sale (Full)","amount_range_low":1001,"amount_range_high":15000,"amount_range_label":"$1,001 - $15,000","comment":null,"is_late":0,"days_to_file":13,"ingested_at":"2026-04-18 18:17:58","row_index":null,"notification_received_over_30d":null,"doc_url":"https://efdsearch.senate.gov/search/view/ptr/bbdeaa6d-dcb6-41fa-a5d5-cb5e5d10af6b/","filing_type":"PTR","ret_since":null,"excess_since":null,"ret_30d":null,"ret_1y":null},{"id":"senate_bbdeaa6d-dcb6-41fa-a5d5-cb5e5d10af6b_t87","filing_id":"senate_bbdeaa6d-dcb6-41fa-a5d5-cb5e5d10af6b","filer_id":"senate_thomasr_tillis","source_id":"senate_efd","transaction_date":"2015-02-13","notification_date":null,"filing_date":"2015-02-26","owner":"Joint","ticker":"ALE","asset_name":"ALLETE, Inc. (NYSE)","asset_type":"Stock","transaction_type":"Sale (Full)","amount_range_low":1001,"amount_range_high":15000,"amount_range_label":"$1,001 - $15,000","comment":null,"is_late":0,"days_to_file":13,"ingested_at":"2026-04-18 18:17:58","row_index":null,"notification_received_over_30d":null,"doc_url":"https://efdsearch.senate.gov/search/view/ptr/bbdeaa6d-dcb6-41fa-a5d5-cb5e5d10af6b/","filing_type":"PTR","ret_since":null,"excess_since":null,"ret_30d":null,"ret_1y":null},{"id":"senate_bbdeaa6d-dcb6-41fa-a5d5-cb5e5d10af6b_t88","filing_id":"senate_bbdeaa6d-dcb6-41fa-a5d5-cb5e5d10af6b","filer_id":"senate_thomasr_tillis","source_id":"senate_efd","transaction_date":"2015-02-13","notification_date":null,"filing_date":"2015-02-26","owner":"Joint","ticker":"AKRX","asset_name":"Akorn, Inc. (NASDAQ)","asset_type":"Stock","transaction_type":"Sale (Full)","amount_range_low":1001,"amount_range_high":15000,"amount_range_label":"$1,001 - $15,000","comment":null,"is_late":0,"days_to_file":13,"ingested_at":"2026-04-18 18:17:58","row_index":null,"notification_received_over_30d":null,"doc_url":"https://efdsearch.senate.gov/search/view/ptr/bbdeaa6d-dcb6-41fa-a5d5-cb5e5d10af6b/","filing_type":"PTR","ret_since":null,"excess_since":null,"ret_30d":null,"ret_1y":null},{"id":"senate_bbdeaa6d-dcb6-41fa-a5d5-cb5e5d10af6b_t89","filing_id":"senate_bbdeaa6d-dcb6-41fa-a5d5-cb5e5d10af6b","filer_id":"senate_thomasr_tillis","source_id":"senate_efd","transaction_date":"2015-02-13","notification_date":null,"filing_date":"2015-02-26","owner":"Joint","ticker":"AFSI","asset_name":"AmTrust Financial Services, Inc. (NASDAQ)","asset_type":"Stock","transaction_type":"Sale (Full)","amount_range_low":1001,"amount_range_high":15000,"amount_range_label":"$1,001 - $15,000","comment":null,"is_late":0,"days_to_file":13,"ingested_at":"2026-04-18 18:17:58","row_index":null,"notification_received_over_30d":null,"doc_url":"https://efdsearch.senate.gov/search/view/ptr/bbdeaa6d-dcb6-41fa-a5d5-cb5e5d10af6b/","filing_type":"PTR","ret_since":-46.94244458706107,"excess_since":-72.82194161291372,"ret_30d":1.1151128841678122,"ret_1y":-8.453232153288262},{"id":"senate_bbdeaa6d-dcb6-41fa-a5d5-cb5e5d10af6b_t90","filing_id":"senate_bbdeaa6d-dcb6-41fa-a5d5-cb5e5d10af6b","filer_id":"senate_thomasr_tillis","source_id":"senate_efd","transaction_date":"2015-02-13","notification_date":null,"filing_date":"2015-02-26","owner":"Joint","ticker":"ABCO","asset_name":"The Advisory Board Company (NASDAQ)","asset_type":"Stock","transaction_type":"Sale (Full)","amount_range_low":1001,"amount_range_high":15000,"amount_range_label":"$1,001 - $15,000","comment":null,"is_late":0,"days_to_file":13,"ingested_at":"2026-04-18 18:17:58","row_index":null,"notification_received_over_30d":null,"doc_url":"https://efdsearch.senate.gov/search/view/ptr/bbdeaa6d-dcb6-41fa-a5d5-cb5e5d10af6b/","filing_type":"PTR","ret_since":null,"excess_since":null,"ret_30d":null,"ret_1y":null},{"id":"senate_bbdeaa6d-dcb6-41fa-a5d5-cb5e5d10af6b_t91","filing_id":"senate_bbdeaa6d-dcb6-41fa-a5d5-cb5e5d10af6b","filer_id":"senate_thomasr_tillis","source_id":"senate_efd","transaction_date":"2015-02-13","notification_date":null,"filing_date":"2015-02-26","owner":"Joint","ticker":"AAT","asset_name":"American Assets Trust, Inc. (NYSE)","asset_type":"Stock","transaction_type":"Sale (Full)","amount_range_low":1001,"amount_range_high":15000,"amount_range_label":"$1,001 - $15,000","comment":null,"is_late":0,"days_to_file":13,"ingested_at":"2026-04-18 18:17:58","row_index":null,"notification_received_over_30d":null,"doc_url":"https://efdsearch.senate.gov/search/view/ptr/bbdeaa6d-dcb6-41fa-a5d5-cb5e5d10af6b/","filing_type":"PTR","ret_since":null,"excess_since":null,"ret_30d":null,"ret_1y":null},{"id":"senate_bbdeaa6d-dcb6-41fa-a5d5-cb5e5d10af6b_t92","filing_id":"senate_bbdeaa6d-dcb6-41fa-a5d5-cb5e5d10af6b","filer_id":"senate_thomasr_tillis","source_id":"senate_efd","transaction_date":"2015-02-13","notification_date":null,"filing_date":"2015-02-26","owner":"Joint","ticker":"AAON","asset_name":"AAON Inc. (NASDAQ)","asset_type":"Stock","transaction_type":"Sale (Full)","amount_range_low":1001,"amount_range_high":15000,"amount_range_label":"$1,001 - $15,000","comment":null,"is_late":0,"days_to_file":13,"ingested_at":"2026-04-18 18:17:58","row_index":null,"notification_received_over_30d":null,"doc_url":"https://efdsearch.senate.gov/search/view/ptr/bbdeaa6d-dcb6-41fa-a5d5-cb5e5d10af6b/","filing_type":"PTR","ret_since":799.8716151141832,"excess_since":539.2652728171659,"ret_30d":-3.936667210632379,"ret_1y":-10.397945401104524},{"id":"senate_bbdeaa6d-dcb6-41fa-a5d5-cb5e5d10af6b_t93","filing_id":"senate_bbdeaa6d-dcb6-41fa-a5d5-cb5e5d10af6b","filer_id":"senate_thomasr_tillis","source_id":"senate_efd","transaction_date":"2015-02-05","notification_date":null,"filing_date":"2015-02-26","owner":"Joint","ticker":"NICE","asset_name":"NICE Systems Ltd. (NASDAQ)","asset_type":"Stock","transaction_type":"Sale (Full)","amount_range_low":1001,"amount_range_high":15000,"amount_range_label":"$1,001 - $15,000","comment":null,"is_late":0,"days_to_file":21,"ingested_at":"2026-04-18 18:17:58","row_index":null,"notification_received_over_30d":null,"doc_url":"https://efdsearch.senate.gov/search/view/ptr/bbdeaa6d-dcb6-41fa-a5d5-cb5e5d10af6b/","filing_type":"PTR","ret_since":58.682522501349865,"excess_since":-202.46148695063073,"ret_30d":14.08078359556317,"ret_1y":8.795771777417812}]}